Workbook

Sheet Inputs
A1: SOURCES & USES MODEL — INPUTS
A2: Hypothetical M&A deal: Kotak Mahindra Bank (Acquirer) acquires IDFC First Bank (Target) | All financials in ₹ Crore | FY2026 actuals
A3: 🔵 Blue = typed input 🟢 Green = calculated formula 🟣 Purple = live price via Power Query (Data → Refresh All)
A5: ① ACQUIRER — KOTAK MAHINDRA BANK LTD (NSE: KOTAKBANK)
A6: Acquirer Net Profit, FY2026 (₹ Cr) | B6: 19288 | C6: Source: Kotak Q4FY26 results (consolidated), May 2026
A7: Acquirer Shares Outstanding (Crore shares) | B7: 198.86 | C7: Source: NSE / Kotak investor relations, FY2026
A8: Acquirer Current Share Price (₹) [LIVE — refreshes from NSE via Yahoo Finance] | B8: =IFERROR(acquirerliveprice,2050) -> 2050 | C8: Power Query named range: AcquirerLivePrice | Fallback: ₹2,050 if offline
A9: Acquirer Cash & Equivalents (₹ Cr) | B9: 12500 | C9: Approximate liquid reserves; adjust from latest balance sheet
A10: Acquirer Pre-Provision Operating Profit / PPOP (₹ Cr) | B10: 24800 | C10: Bank proxy for EBITDA — Kotak FY2026 estimate
A11: Acquirer Existing Net Borrowings (₹ Cr) | B11: 185000 | C11: Net borrowings (bonds, sub-debt, refinance) excl. deposits
A13: ② TARGET — IDFC FIRST BANK LTD (NSE: IDFCFIRSTB)
A14: Target Net Profit, FY2026 (₹ Cr) | B14: 1636 | C14: Source: IDFC First Bank Q4FY26 standalone results, Apr 2026
A15: Target Shares Outstanding (Crore shares) | B15: 860.83 | C15: Source: IDFC First Bank ESOS filing, May 2026
A16: Target Current Share Price (₹) [LIVE — refreshes from NSE via Yahoo Finance] | B16: =IFERROR(targetliveprice,68.5) -> 68.5 | C16: Power Query named range: TargetLivePrice | Fallback: ₹68.50 if offline
A17: Target PPOP / Pre-Provision Operating Profit (₹ Cr) | B17: 4800 | C17: IDFC First Bank FY2026 estimate (HSBC research)
A18: Target Existing Net Borrowings (₹ Cr) | B18: 48354 | C18: Source: IDFC First Bank Q3FY26 investor presentation (borrowings)
A20: ③ DEAL STRUCTURE
A21: Offer Premium to Target Current Market Price (%) | B21: 0.3 | C21: Typical Indian bank M&A premium range: 20–40%
A22: Offer Price per Target Share (₹) [calculated] | B22: =B16*(1+B21) -> 89.05 | C22: Offer price = Target live price × (1 + premium)
A23: Equity Purchase Price (₹ Cr) [calculated — live price × shares × (1+premium)] | B23: =B22*B15 -> 76656.912 | C23: Equity purchase price = Offer price × shares outstanding
A24: % Consideration paid in Cash | B24: 0.6 | C24: Adjust: 100% cash = all debt/BS-cash funded; 0% = all stock swap
A25: % Consideration paid in Stock [calculated] | B25: =1-B24 -> 0.4
A26: % of Cash portion funded by New Debt | B26: 0.7 | C26: RBI-regulated; typical for Indian bank acquisitions
A27: % of Cash portion funded by Balance-Sheet Cash [calculated] | B27: =1-B26 -> 0.3
A28: New Debt Interest Rate (% p.a.) | B28: 0.075 | C28: Approx. Indian bond/NCD rate, Jul 2026 environment
A29: Foregone Yield on Cash Used (% p.a.) | B29: 0.065 | C29: Opportunity cost of using balance-sheet cash (T-bill / liquid fund rate)
A30: Acquirer Effective Tax Rate (%) | B30: 0.2517 | C30: New domestic tax regime for large Indian banks, FY2026
A31: Integration / Transaction Costs (₹ Cr) | B31: 850 | C31: Advisory, stamp duty, tech integration, branch rationalisation
A33: ④ SYNERGIES
A34: Run-Rate Annual Synergies (₹ Cr, pre-tax) | B34: 2200 | C34: Cost + revenue synergies: branch overlap, funding cost, cross-sell
A35: Synergy Ramp — Year 1 (% of run-rate) | B35: 0.15
A36: Synergy Ramp — Year 2 (% of run-rate) | B36: 0.4
A37: Synergy Ramp — Year 3 (% of run-rate) | B37: 0.7
A38: Synergy Ramp — Year 4 (% of run-rate) | B38: 0.9
A39: Synergy Ramp — Year 5 (% of run-rate) | B39: 1
A41: ⑤ LEVERAGE & COVENANT (RBI-STYLE)
A42: Net Borrowings / PPOP Covenant Threshold (x) | B42: 8 | C42: Indicative internal threshold; RBI monitors leverage via CRAR separately

Sheet Calculations
A1: CALCULATIONS — PRO FORMA ACCRETION / DILUTION ANALYSIS
A2: Kotak Mahindra Bank (Acquirer) acquires IDFC First Bank (Target) | All values in ₹ Crore | Formulas reference Inputs tab — change any input and this sheet recalculates
A4: A · DEAL SIZE MECHANICS
A5: Equity Purchase Price (₹ Cr) | B5: =Inputs!B23 -> 76656.912
A6: Cash Consideration (₹ Cr) | B6: =Inputs!B23*Inputs!B24 -> 45994.147
A7: Stock Consideration (₹ Cr) | B7: =Inputs!B23*Inputs!B25 -> 30662.765
A8: New Debt Raised (₹ Cr) | B8: =Calculations!B6*Inputs!B26 -> 32195.903
A9: Balance-Sheet Cash Used (₹ Cr) | B9: =Calculations!B6*Inputs!B27 -> 13798.244
A10: New Shares Issued to Target Shareholders (Crore shares) | B10: =Calculations!B7/Inputs!B8 -> 14.957446
A11: Pro Forma Shares Outstanding (Crore shares) | B11: =Inputs!B7+Calculations!B10 -> 213.81745
A13: B · ANNUAL FINANCING COST IMPACT (after-tax, ₹ Cr)
A14: Incremental Interest on New Debt — pre-tax (₹ Cr) | B14: =Calculations!B8*Inputs!B28 -> 2414.6927
A15: Incremental Interest on New Debt — after-tax (₹ Cr) | B15: =Calculations!B14*(1-Inputs!B30) -> 1806.9146
A16: Foregone Yield on Cash Used — pre-tax (₹ Cr) | B16: =Calculations!B9*Inputs!B29 -> 896.88586
A17: Foregone Yield on Cash Used — after-tax (₹ Cr) | B17: =Calculations!B16*(1-Inputs!B30) -> 671.13969
A18: Total Annual Financing Drag — after-tax (₹ Cr) | B18: =Calculations!B15+Calculations!B17 -> 2478.0542
A20: C · AFTER-TAX SYNERGY SCHEDULE (₹ Cr)
B21: Year 1 | C21: Year 2 | D21: Year 3 | E21: Year 4 | F21: Year 5
A22: Synergy Ramp (% of run-rate) | B22: =Inputs!B35 -> 0.15 | C22: =Inputs!B36 -> 0.4 | D22: =Inputs!B37 -> 0.7 | E22: =Inputs!B38 -> 0.9 | F22: =Inputs!B39 -> 1
A23: Pre-Tax Synergies (₹ Cr) | B23: =Inputs!B34*Inputs!B35 -> 330 | C23: =Inputs!B34*Inputs!B36 -> 880 | D23: =Inputs!B34*Inputs!B37 -> 1540 | E23: =Inputs!B34*Inputs!B38 -> 1980 | F23: =Inputs!B34*Inputs!B39 -> 2200
A24: After-Tax Synergies (₹ Cr) | B24: =Calculations!B23*(1-Inputs!B30) -> 246.939 | C24: =Calculations!C23*(1-Inputs!B30) -> 658.504 | D24: =Calculations!D23*(1-Inputs!B30) -> 1152.382 | E24: =Calculations!E23*(1-Inputs!B30) -> 1481.634 | F24: =Calculations!F23*(1-Inputs!B30) -> 1646.26
A26: D · PRO FORMA NET PROFIT BUILD (₹ Cr)
B27: Year 1 | C27: Year 2 | D27: Year 3 | E27: Year 4 | F27: Year 5
A28: (+) Acquirer Standalone Net Profit (₹ Cr) | B28: =Inputs!B6 -> 19288 | C28: =Inputs!B6 -> 19288 | D28: =Inputs!B6 -> 19288 | E28: =Inputs!B6 -> 19288 | F28: =Inputs!B6 -> 19288
A29: (+) Target Net Profit (₹ Cr) | B29: =Inputs!B14 -> 1636 | C29: =Inputs!B14 -> 1636 | D29: =Inputs!B14 -> 1636 | E29: =Inputs!B14 -> 1636 | F29: =Inputs!B14 -> 1636
A30: (+) After-Tax Synergies (₹ Cr) | B30: =Calculations!B24 -> 246.939 | C30: =Calculations!C24 -> 658.504 | D30: =Calculations!D24 -> 1152.382 | E30: =Calculations!E24 -> 1481.634 | F30: =Calculations!F24 -> 1646.26
A31: (−) After-Tax Financing Drag (₹ Cr) | B31: =Calculations!B18 -> 2478.0542 | C31: =Calculations!B18 -> 2478.0542 | D31: =Calculations!B18 -> 2478.0542 | E31: =Calculations!B18 -> 2478.0542 | F31: =Calculations!B18 -> 2478.0542
A32: Pro Forma Net Profit (₹ Cr) | B32: =Calculations!B28+Calculations!B29+Calculations!B30-Calculations!B31 -> 18692.885 | C32: =Calculations!C28+Calculations!C29+Calculations!C30-Calculations!C31 -> 19104.45 | D32: =Calculations!D28+Calculations!D29+Calculations!D30-Calculations!D31 -> 19598.328 | E32: =Calculations!E28+Calculations!E29+Calculations!E30-Calculations!E31 -> 19927.58 | F32: =Calculations!F28+Calculations!F29+Calculations!F30-Calculations!F31 -> 20092.206
A34: E · EPS BRIDGE & ACCRETION / DILUTION
B35: Standalone | C35: Year 1 | D35: Year 2 | E35: Year 3 | F35: Year 4 | G35: Year 5
A36: Net Profit (₹ Cr) | B36: =Inputs!B6 -> 19288 | C36: =Calculations!B32 -> 18692.885 | D36: =Calculations!C32 -> 19104.45 | E36: =Calculations!D32 -> 19598.328 | F36: =Calculations!E32 -> 19927.58 | G36: =Calculations!F32 -> 20092.206
A37: Shares Outstanding (Crore) | B37: =Inputs!B7 -> 198.86 | C37: =Calculations!B11 -> 213.81745 | D37: =Calculations!B11 -> 213.81745 | E37: =Calculations!B11 -> 213.81745 | F37: =Calculations!B11 -> 213.81745 | G37: =Calculations!B11 -> 213.81745
A38: EPS (₹ per share) | B38: =Calculations!B36/(Inputs!B7*100) -> 0.96992859 | C38: =Calculations!B32/(Calculations!B11*100) -> 0.87424507 | D38: =Calculations!C32/(Calculations!B11*100) -> 0.8934935 | E38: =Calculations!D32/(Calculations!B11*100) -> 0.91659161 | F38: =Calculations!E32/(Calculations!B11*100) -> 0.93199035 | G38: =Calculations!F32/(Calculations!B11*100) -> 0.93968973
A39: Accretion / (Dilution) — ₹ per share | B39: — | C39: =Calculations!C38-Calculations!B38 -> -0.095683526 | D39: =Calculations!D38-Calculations!B38 -> -0.076435097 | E39: =Calculations!E38-Calculations!B38 -> -0.053336982 | F39: =Calculations!F38-Calculations!B38 -> -0.037938238 | G39: =Calculations!G38-Calculations!B38 -> -0.030238866
A40: Accretion / (Dilution) — % of Standalone EPS | B40: — | C40: =(Calculations!C38-Calculations!B38)/Calculations!B38 -> -0.098650073 | D40: =(Calculations!D38-Calculations!B38)/Calculations!B38 -> -0.07880487 | E40: =(Calculations!E38-Calculations!B38)/Calculations!B38 -> -0.054990627 | F40: =(Calculations!F38-Calculations!B38)/Calculations!B38 -> -0.039114465 | G40: =(Calculations!G38-Calculations!B38)/Calculations!B38 -> -0.031176384
A42: F · OUTPUT RANGE — Power BI & Tableau connect to this block (named range: OutputTable)
A43: Metric | B43: Standalone | C43: Year 1 | D43: Year 2 | E43: Year 3 | F43: Year 4 | G43: Year 5
A44: Acquirer Standalone Net Profit (₹ Cr) | B44: =Inputs!B6 -> 19288 | C44: =Inputs!B6 -> 19288 | D44: =Inputs!B6 -> 19288 | E44: =Inputs!B6 -> 19288 | F44: =Inputs!B6 -> 19288 | G44: =Inputs!B6 -> 19288
A45: Target Net Profit (₹ Cr) | B45: =Inputs!B14 -> 1636 | C45: =Inputs!B14 -> 1636 | D45: =Inputs!B14 -> 1636 | E45: =Inputs!B14 -> 1636 | F45: =Inputs!B14 -> 1636 | G45: =Inputs!B14 -> 1636
A46: After-Tax Synergies (₹ Cr) | B46: — | C46: =Calculations!B24 -> 246.939 | D46: =Calculations!C24 -> 658.504 | E46: =Calculations!D24 -> 1152.382 | F46: =Calculations!E24 -> 1481.634 | G46: =Calculations!F24 -> 1646.26
A47: After-Tax Financing Drag (₹ Cr) | B47: =Calculations!B18 -> 2478.0542 | C47: =Calculations!B18 -> 2478.0542 | D47: =Calculations!B18 -> 2478.0542 | E47: =Calculations!B18 -> 2478.0542 | F47: =Calculations!B18 -> 2478.0542 | G47: =Calculations!B18 -> 2478.0542
A48: Pro Forma Net Profit (₹ Cr) | B48: =Calculations!B32 -> 18692.885 | C48: =Calculations!B32 -> 18692.885 | D48: =Calculations!C32 -> 19104.45 | E48: =Calculations!D32 -> 19598.328 | F48: =Calculations!E32 -> 19927.58 | G48: =Calculations!F32 -> 20092.206
A49: Pro Forma Shares (Crore) | B49: =Inputs!B7 -> 198.86 | C49: =Calculations!B11 -> 213.81745 | D49: =Calculations!B11 -> 213.81745 | E49: =Calculations!B11 -> 213.81745 | F49: =Calculations!B11 -> 213.81745 | G49: =Calculations!B11 -> 213.81745
A50: Standalone EPS (₹) | B50: =Calculations!B38 -> 0.96992859 | C50: =Calculations!B38 -> 0.96992859 | D50: =Calculations!B38 -> 0.96992859 | E50: =Calculations!B38 -> 0.96992859 | F50: =Calculations!B38 -> 0.96992859 | G50: =Calculations!B38 -> 0.96992859
A51: Pro Forma EPS (₹) | B51: =Calculations!B38 -> 0.96992859 | C51: =Calculations!C38 -> 0.87424507 | D51: =Calculations!D38 -> 0.8934935 | E51: =Calculations!E38 -> 0.91659161 | F51: =Calculations!F38 -> 0.93199035 | G51: =Calculations!G38 -> 0.93968973
A52: Accretion / (Dilution) % | B52: — | C52: =Calculations!C40 -> -0.098650073 | D52: =Calculations!D40 -> -0.07880487 | E52: =Calculations!E40 -> -0.054990627 | F52: =Calculations!F40 -> -0.039114465 | G52: =Calculations!G40 -> -0.031176384
A53: New Debt Raised (₹ Cr) | B53: =Calculations!B8 -> 32195.903 | C53: =Calculations!B8 -> 32195.903 | D53: =Calculations!B8 -> 32195.903 | E53: =Calculations!B8 -> 32195.903 | F53: =Calculations!B8 -> 32195.903 | G53: =Calculations!B8 -> 32195.903
A54: BS Cash Used (₹ Cr) | B54: =Calculations!B9 -> 13798.244 | C54: =Calculations!B9 -> 13798.244 | D54: =Calculations!B9 -> 13798.244 | E54: =Calculations!B9 -> 13798.244 | F54: =Calculations!B9 -> 13798.244 | G54: =Calculations!B9 -> 13798.244
A55: Equity Purchase Price (₹ Cr) | B55: =Inputs!B23 -> 76656.912 | C55: =Inputs!B23 -> 76656.912 | D55: =Inputs!B23 -> 76656.912 | E55: =Inputs!B23 -> 76656.912 | F55: =Inputs!B23 -> 76656.912 | G55: =Inputs!B23 -> 76656.912
A56: Offer Premium (%) | B56: =Inputs!B21 -> 0.3 | C56: =Inputs!B21 -> 0.3 | D56: =Inputs!B21 -> 0.3 | E56: =Inputs!B21 -> 0.3 | F56: =Inputs!B21 -> 0.3 | G56: =Inputs!B21 -> 0.3
A57: % Consideration Cash | B57: =Inputs!B24 -> 0.6 | C57: =Inputs!B24 -> 0.6 | D57: =Inputs!B24 -> 0.6 | E57: =Inputs!B24 -> 0.6 | F57: =Inputs!B24 -> 0.6 | G57: =Inputs!B24 -> 0.6
A58: % Consideration Stock | B58: =Inputs!B25 -> 0.4 | C58: =Inputs!B25 -> 0.4 | D58: =Inputs!B25 -> 0.4 | E58: =Inputs!B25 -> 0.4 | F58: =Inputs!B25 -> 0.4 | G58: =Inputs!B25 -> 0.4

Sheet Sources & Uses
B3: SOURCES & USES OF FUNDS — ILLUSTRATIVE TRANSACTION ANALYSIS
B4: Kotak Mahindra Bank Ltd (Acquirer) × IDFC First Bank Ltd (Target)
B5: All figures in ₹ Crore | FY2026 actuals | Hypothetical / Illustrative only | E5: Deal structure reflects Inputs tab assumptions — updates automatically
B7: USES OF FUNDS | E7: SOURCES OF FUNDS
B8: Equity Purchase Price | C8: =Inputs!B23 -> 76656.912 | E8: New Debt Raised | F8: =Calculations!B8 -> 32195.903
B9: ↳ Cash Consideration | C9: =Calculations!B6 -> 45994.147 | E9: Balance-Sheet Cash Used | F9: =Calculations!B9 -> 13798.244
B10: ↳ Stock Consideration (at Kotak share price) | C10: =Calculations!B7 -> 30662.765 | E10: New Equity Issued (Stock Consideration) | F10: =Calculations!B7 -> 30662.765
B11: Control Premium Paid (above target market cap) | C11: =Inputs!B23*Inputs!B21/(1+Inputs!B21) -> 17690.056 | E11: Integration Costs (funded from cash / debt) | F11: =Inputs!B31 -> 850
B12: Integration & Transaction Costs | C12: =Inputs!B31 -> 850
B14: TOTAL USES | C14: =Inputs!B23+Inputs!B31 -> 77506.912 | E14: TOTAL SOURCES | F14: =Calculations!B8+Calculations!B9+Calculations!B7+Inputs!B31 -> 77506.912
B16: CHECK — Sources minus Uses (must equal zero) | E16: Sources − Uses = | F16: =F14-C14 -> 0
E17: ✔ Green = balanced | ✘ Red = sources ≠ uses (check inputs)
B20: KEY DEAL METRICS — DERIVED FROM INPUTS
B21: Offer Price per Share | C21: Offer Premium | D21: % Cash | E21: % Stock | F21: New Shares Issued (Cr)
B22: =Inputs!B22 -> 89.05 | C22: =Inputs!B21 -> 0.3 | D22: =Inputs!B24 -> 0.6 | E22: =Inputs!B25 -> 0.4 | F22: =Calculations!B10 -> 14.957446
B24: STRICTLY CONFIDENTIAL — FOR ILLUSTRATIVE & EDUCATIONAL PURPOSES ONLY | NOT FOR DISTRIBUTION | Sources & Uses — An Integrated M&A Decision Platform

Sheet Sensitivity
B1: SENSITIVITY ANALYSIS — YEAR 1 & YEAR 3 ACCRETION / (DILUTION) %
B2: Axes: Offer Premium % (rows, 15%→45%) × Cash Consideration % (cols, 0%→100%) | 🟡 = current Inputs assumption | Green = accretive | Red = dilutive
B4: TABLE 1 — YEAR 1 ACCRETION / (DILUTION) %
B5: Row input: Offer Premium | Column input: % Cash Consideration | Formula independent — no Excel Data Table engine required
B6: Premium ↓ / Cash % → | C6: 0 | D6: 0.1 | E6: 0.2 | F6: 0.3 | G6: 0.4 | H6: 0.5 | I6: 0.6 | J6: 0.7 | K6: 0.8 | L6: 0.9 | M6: 1
B7: 0.15 | C7: =(((Inputs!B6+Inputs!B14+(Inputs!B34*Inputs!B35*(1-Inputs!B30))-(((Inputs!B16*(1+0.15)*Inputs!B15)*0*Inputs!B26*Inputs!B28+(Inputs!B16*(1+0.15)*Inputs!B15)*0*Inputs!B27*Inputs!B29)*(1-Inputs!B30)))/((Inputs!B7+((Inputs!B16*(1+0.15)*Inputs!B15)*(1-0)/Inputs!B8))*100))-(Inputs!B6/(Inputs!B7*100)))/(Inputs!B6/(Inputs!B7*100)) -> -0.058919793 | D7: =(((Inputs!B6+Inputs!B14+(Inputs!B34*Inputs!B35*(1-Inputs!B30))-(((Inputs!B16*(1+0.15)*Inputs!B15)*0.1*Inputs!B26*Inputs!B28+(Inputs!B16*(1+0.15)*Inputs!B15)*0.1*Inputs!B27*Inputs!B29)*(1-Inputs!B30)))/((Inputs!B7+((Inputs!B16*(1+0.15)*Inputs!B15)*(1-0.1)/Inputs!B8))*100))-(Inputs!B6/(Inputs!B7*100)))/(Inputs!B6/(Inputs!B7*100)) -> -0.061779505 | E7: =(((Inputs!B6+Inputs!B14+(Inputs!B34*Inputs!B35*(1-Inputs!B30))-(((Inputs!B16*(1+0.15)*Inputs!B15)*0.2*Inputs!B26*Inputs!B28+(Inputs!B16*(1+0.15)*Inputs!B15)*0.2*Inputs!B27*Inputs!B29)*(1-Inputs!B30)))/((Inputs!B7+((Inputs!B16*(1+0.15)*Inputs!B15)*(1-0.2)/Inputs!B8))*100))-(Inputs!B6/(Inputs!B7*100)))/(Inputs!B6/(Inputs!B7*100)) -> -0.064723181 | F7: =(((Inputs!B6+Inputs!B14+(Inputs!B34*Inputs!B35*(1-Inputs!B30))-(((Inputs!B16*(1+0.15)*Inputs!B15)*0.3*Inputs!B26*Inputs!B28+(Inputs!B16*(1+0.15)*Inputs!B15)*0.3*Inputs!B27*Inputs!B29)*(1-Inputs!B30)))/((Inputs!B7+((Inputs!B16*(1+0.15)*Inputs!B15)*(1-0.3)/Inputs!B8))*100))-(Inputs!B6/(Inputs!B7*100)))/(Inputs!B6/(Inputs!B7*100)) -> -0.067754575 | G7: =(((Inputs!B6+Inputs!B14+(Inputs!B34*Inputs!B35*(1-Inputs!B30))-(((Inputs!B16*(1+0.15)*Inputs!B15)*0.4*Inputs!B26*Inputs!B28+(Inputs!B16*(1+0.15)*Inputs!B15)*0.4*Inputs!B27*Inputs!B29)*(1-Inputs!B30)))/((Inputs!B7+((Inputs!B16*(1+0.15)*Inputs!B15)*(1-0.4)/Inputs!B8))*100))-(Inputs!B6/(Inputs!B7*100)))/(Inputs!B6/(Inputs!B7*100)) -> -0.070877667 | H7: =(((Inputs!B6+Inputs!B14+(Inputs!B34*Inputs!B35*(1-Inputs!B30))-(((Inputs!B16*(1+0.15)*Inputs!B15)*0.5*Inputs!B26*Inputs!B28+(Inputs!B16*(1+0.15)*Inputs!B15)*0.5*Inputs!B27*Inputs!B29)*(1-Inputs!B30)))/((Inputs!B7+((Inputs!B16*(1+0.15)*Inputs!B15)*(1-0.5)/Inputs!B8))*100))-(Inputs!B6/(Inputs!B7*100)))/(Inputs!B6/(Inputs!B7*100)) -> -0.074096682 | I7: =(((Inputs!B6+Inputs!B14+(Inputs!B34*Inputs!B35*(1-Inputs!B30))-(((Inputs!B16*(1+0.15)*Inputs!B15)*0.6*Inputs!B26*Inputs!B28+(Inputs!B16*(1+0.15)*Inputs!B15)*0.6*Inputs!B27*Inputs!B29)*(1-Inputs!B30)))/((Inputs!B7+((Inputs!B16*(1+0.15)*Inputs!B15)*(1-0.6)/Inputs!B8))*100))-(Inputs!B6/(Inputs!B7*100)))/(Inputs!B6/(Inputs!B7*100)) -> -0.077416108 | J7: =(((Inputs!B6+Inputs!B14+(Inputs!B34*Inputs!B35*(1-Inputs!B30))-(((Inputs!B16*(1+0.15)*Inputs!B15)*0.7*Inputs!B26*Inputs!B28+(Inputs!B16*(1+0.15)*Inputs!B15)*0.7*Inputs!B27*Inputs!B29)*(1-Inputs!B30)))/((Inputs!B7+((Inputs!B16*(1+0.15)*Inputs!B15)*(1-0.7)/Inputs!B8))*100))-(Inputs!B6/(Inputs!B7*100)))/(Inputs!B6/(Inputs!B7*100)) -> -0.080840718 | K7: =(((Inputs!B6+Inputs!B14+(Inputs!B34*Inputs!B35*(1-Inputs!B30))-(((Inputs!B16*(1+0.15)*Inputs!B15)*0.8*Inputs!B26*Inputs!B28+(Inputs!B16*(1+0.15)*Inputs!B15)*0.8*Inputs!B27*Inputs!B29)*(1-Inputs!B30)))/((Inputs!B7+((Inputs!B16*(1+0.15)*Inputs!B15)*(1-0.8)/Inputs!B8))*100))-(Inputs!B6/(Inputs!B7*100)))/(Inputs!B6/(Inputs!B7*100)) -> -0.084375592 | L7: =(((Inputs!B6+Inputs!B14+(Inputs!B34*Inputs!B35*(1-Inputs!B30))-(((Inputs!B16*(1+0.15)*Inputs!B15)*0.9*Inputs!B26*Inputs!B28+(Inputs!B16*(1+0.15)*Inputs!B15)*0.9*Inputs!B27*Inputs!B29)*(1-Inputs!B30)))/((Inputs!B7+((Inputs!B16*(1+0.15)*Inputs!B15)*(1-0.9)/Inputs!B8))*100))-(Inputs!B6/(Inputs!B7*100)))/(Inputs!B6/(Inputs!B7*100)) -> -0.088026141 | M7: =(((Inputs!B6+Inputs!B14+(Inputs!B34*Inputs!B35*(1-Inputs!B30))-(((Inputs!B16*(1+0.15)*Inputs!B15)*1*Inputs!B26*Inputs!B28+(Inputs!B16*(1+0.15)*Inputs!B15)*1*Inputs!B27*Inputs!B29)*(1-Inputs!B30)))/((Inputs!B7+((Inputs!B16*(1+0.15)*Inputs!B15)*(1-1)/Inputs!B8))*100))-(Inputs!B6/(Inputs!B7*100)))/(Inputs!B6/(Inputs!B7*100)) -> -0.09179814
B8: 0.2 | C8: =(((Inputs!B6+Inputs!B14+(Inputs!B34*Inputs!B35*(1-Inputs!B30))-(((Inputs!B16*(1+0.2)*Inputs!B15)*0*Inputs!B26*Inputs!B28+(Inputs!B16*(1+0.2)*Inputs!B15)*0*Inputs!B27*Inputs!B29)*(1-Inputs!B30)))/((Inputs!B7+((Inputs!B16*(1+0.2)*Inputs!B15)*(1-0)/Inputs!B8))*100))-(Inputs!B6/(Inputs!B7*100)))/(Inputs!B6/(Inputs!B7*100)) -> -0.064719318 | D8: =(((Inputs!B6+Inputs!B14+(Inputs!B34*Inputs!B35*(1-Inputs!B30))-(((Inputs!B16*(1+0.2)*Inputs!B15)*0.1*Inputs!B26*Inputs!B28+(Inputs!B16*(1+0.2)*Inputs!B15)*0.1*Inputs!B27*Inputs!B29)*(1-Inputs!B30)))/((Inputs!B7+((Inputs!B16*(1+0.2)*Inputs!B15)*(1-0.1)/Inputs!B8))*100))-(Inputs!B6/(Inputs!B7*100)))/(Inputs!B6/(Inputs!B7*100)) -> -0.067773629 | E8: =(((Inputs!B6+Inputs!B14+(Inputs!B34*Inputs!B35*(1-Inputs!B30))-(((Inputs!B16*(1+0.2)*Inputs!B15)*0.2*Inputs!B26*Inputs!B28+(Inputs!B16*(1+0.2)*Inputs!B15)*0.2*Inputs!B27*Inputs!B29)*(1-Inputs!B30)))/((Inputs!B7+((Inputs!B16*(1+0.2)*Inputs!B15)*(1-0.2)/Inputs!B8))*100))-(Inputs!B6/(Inputs!B7*100)))/(Inputs!B6/(Inputs!B7*100)) -> -0.070921043 | F8: =(((Inputs!B6+Inputs!B14+(Inputs!B34*Inputs!B35*(1-Inputs!B30))-(((Inputs!B16*(1+0.2)*Inputs!B15)*0.3*Inputs!B26*Inputs!B28+(Inputs!B16*(1+0.2)*Inputs!B15)*0.3*Inputs!B27*Inputs!B29)*(1-Inputs!B30)))/((Inputs!B7+((Inputs!B16*(1+0.2)*Inputs!B15)*(1-0.3)/Inputs!B8))*100))-(Inputs!B6/(Inputs!B7*100)))/(Inputs!B6/(Inputs!B7*100)) -> -0.074165882 | G8: =(((Inputs!B6+Inputs!B14+(Inputs!B34*Inputs!B35*(1-Inputs!B30))-(((Inputs!B16*(1+0.2)*Inputs!B15)*0.4*Inputs!B26*Inputs!B28+(Inputs!B16*(1+0.2)*Inputs!B15)*0.4*Inputs!B27*Inputs!B29)*(1-Inputs!B30)))/((Inputs!B7+((Inputs!B16*(1+0.2)*Inputs!B15)*(1-0.4)/Inputs!B8))*100))-(Inputs!B6/(Inputs!B7*100)))/(Inputs!B6/(Inputs!B7*100)) -> -0.077512742 | H8: =(((Inputs!B6+Inputs!B14+(Inputs!B34*Inputs!B35*(1-Inputs!B30))-(((Inputs!B16*(1+0.2)*Inputs!B15)*0.5*Inputs!B26*Inputs!B28+(Inputs!B16*(1+0.2)*Inputs!B15)*0.5*Inputs!B27*Inputs!B29)*(1-Inputs!B30)))/((Inputs!B7+((Inputs!B16*(1+0.2)*Inputs!B15)*(1-0.5)/Inputs!B8))*100))-(Inputs!B6/(Inputs!B7*100)))/(Inputs!B6/(Inputs!B7*100)) -> -0.080966509 | I8: =(((Inputs!B6+Inputs!B14+(Inputs!B34*Inputs!B35*(1-Inputs!B30))-(((Inputs!B16*(1+0.2)*Inputs!B15)*0.6*Inputs!B26*Inputs!B28+(Inputs!B16*(1+0.2)*Inputs!B15)*0.6*Inputs!B27*Inputs!B29)*(1-Inputs!B30)))/((Inputs!B7+((Inputs!B16*(1+0.2)*Inputs!B15)*(1-0.6)/Inputs!B8))*100))-(Inputs!B6/(Inputs!B7*100)))/(Inputs!B6/(Inputs!B7*100)) -> -0.08453239 | J8: =(((Inputs!B6+Inputs!B14+(Inputs!B34*Inputs!B35*(1-Inputs!B30))-(((Inputs!B16*(1+0.2)*Inputs!B15)*0.7*Inputs!B26*Inputs!B28+(Inputs!B16*(1+0.2)*Inputs!B15)*0.7*Inputs!B27*Inputs!B29)*(1-Inputs!B30)))/((Inputs!B7+((Inputs!B16*(1+0.2)*Inputs!B15)*(1-0.7)/Inputs!B8))*100))-(Inputs!B6/(Inputs!B7*100)))/(Inputs!B6/(Inputs!B7*100)) -> -0.088215934 | K8: =(((Inputs!B6+Inputs!B14+(Inputs!B34*Inputs!B35*(1-Inputs!B30))-(((Inputs!B16*(1+0.2)*Inputs!B15)*0.8*Inputs!B26*Inputs!B28+(Inputs!B16*(1+0.2)*Inputs!B15)*0.8*Inputs!B27*Inputs!B29)*(1-Inputs!B30)))/((Inputs!B7+((Inputs!B16*(1+0.2)*Inputs!B15)*(1-0.8)/Inputs!B8))*100))-(Inputs!B6/(Inputs!B7*100)))/(Inputs!B6/(Inputs!B7*100)) -> -0.092023061 | L8: =(((Inputs!B6+Inputs!B14+(Inputs!B34*Inputs!B35*(1-Inputs!B30))-(((Inputs!B16*(1+0.2)*Inputs!B15)*0.9*Inputs!B26*Inputs!B28+(Inputs!B16*(1+0.2)*Inputs!B15)*0.9*Inputs!B27*Inputs!B29)*(1-Inputs!B30)))/((Inputs!B7+((Inputs!B16*(1+0.2)*Inputs!B15)*(1-0.9)/Inputs!B8))*100))-(Inputs!B6/(Inputs!B7*100)))/(Inputs!B6/(Inputs!B7*100)) -> -0.095960099 | M8: =(((Inputs!B6+Inputs!B14+(Inputs!B34*Inputs!B35*(1-Inputs!B30))-(((Inputs!B16*(1+0.2)*Inputs!B15)*1*Inputs!B26*Inputs!B28+(Inputs!B16*(1+0.2)*Inputs!B15)*1*Inputs!B27*Inputs!B29)*(1-Inputs!B30)))/((Inputs!B7+((Inputs!B16*(1+0.2)*Inputs!B15)*(1-1)/Inputs!B8))*100))-(Inputs!B6/(Inputs!B7*100)))/(Inputs!B6/(Inputs!B7*100)) -> -0.10003381
B9: 0.25 | C9: =(((Inputs!B6+Inputs!B14+(Inputs!B34*Inputs!B35*(1-Inputs!B30))-(((Inputs!B16*(1+0.25)*Inputs!B15)*0*Inputs!B26*Inputs!B28+(Inputs!B16*(1+0.25)*Inputs!B15)*0*Inputs!B27*Inputs!B29)*(1-Inputs!B30)))/((Inputs!B7+((Inputs!B16*(1+0.25)*Inputs!B15)*(1-0)/Inputs!B8))*100))-(Inputs!B6/(Inputs!B7*100)))/(Inputs!B6/(Inputs!B7*100)) -> -0.070447799 | D9: =(((Inputs!B6+Inputs!B14+(Inputs!B34*Inputs!B35*(1-Inputs!B30))-(((Inputs!B16*(1+0.25)*Inputs!B15)*0.1*Inputs!B26*Inputs!B28+(Inputs!B16*(1+0.25)*Inputs!B15)*0.1*Inputs!B27*Inputs!B29)*(1-Inputs!B30)))/((Inputs!B7+((Inputs!B16*(1+0.25)*Inputs!B15)*(1-0.1)/Inputs!B8))*100))-(Inputs!B6/(Inputs!B7*100)))/(Inputs!B6/(Inputs!B7*100)) -> -0.073700642 | E9: =(((Inputs!B6+Inputs!B14+(Inputs!B34*Inputs!B35*(1-Inputs!B30))-(((Inputs!B16*(1+0.25)*Inputs!B15)*0.2*Inputs!B26*Inputs!B28+(Inputs!B16*(1+0.25)*Inputs!B15)*0.2*Inputs!B27*Inputs!B29)*(1-Inputs!B30)))/((Inputs!B7+((Inputs!B16*(1+0.25)*Inputs!B15)*(1-0.2)/Inputs!B8))*100))-(Inputs!B6/(Inputs!B7*100)))/(Inputs!B6/(Inputs!B7*100)) -> -0.077056249 | F9: =(((Inputs!B6+Inputs!B14+(Inputs!B34*Inputs!B35*(1-Inputs!B30))-(((Inputs!B16*(1+0.25)*Inputs!B15)*0.3*Inputs!B26*Inputs!B28+(Inputs!B16*(1+0.25)*Inputs!B15)*0.3*Inputs!B27*Inputs!B29)*(1-Inputs!B30)))/((Inputs!B7+((Inputs!B16*(1+0.25)*Inputs!B15)*(1-0.3)/Inputs!B8))*100))-(Inputs!B6/(Inputs!B7*100)))/(Inputs!B6/(Inputs!B7*100)) -> -0.080519567 | G9: =(((Inputs!B6+Inputs!B14+(Inputs!B34*Inputs!B35*(1-Inputs!B30))-(((Inputs!B16*(1+0.25)*Inputs!B15)*0.4*Inputs!B26*Inputs!B28+(Inputs!B16*(1+0.25)*Inputs!B15)*0.4*Inputs!B27*Inputs!B29)*(1-Inputs!B30)))/((Inputs!B7+((Inputs!B16*(1+0.25)*Inputs!B15)*(1-0.4)/Inputs!B8))*100))-(Inputs!B6/(Inputs!B7*100)))/(Inputs!B6/(Inputs!B7*100)) -> -0.084095868 | H9: =(((Inputs!B6+Inputs!B14+(Inputs!B34*Inputs!B35*(1-Inputs!B30))-(((Inputs!B16*(1+0.25)*Inputs!B15)*0.5*Inputs!B26*Inputs!B28+(Inputs!B16*(1+0.25)*Inputs!B15)*0.5*Inputs!B27*Inputs!B29)*(1-Inputs!B30)))/((Inputs!B7+((Inputs!B16*(1+0.25)*Inputs!B15)*(1-0.5)/Inputs!B8))*100))-(Inputs!B6/(Inputs!B7*100)))/(Inputs!B6/(Inputs!B7*100)) -> -0.08779077 | I9: =(((Inputs!B6+Inputs!B14+(Inputs!B34*Inputs!B35*(1-Inputs!B30))-(((Inputs!B16*(1+0.25)*Inputs!B15)*0.6*Inputs!B26*Inputs!B28+(Inputs!B16*(1+0.25)*Inputs!B15)*0.6*Inputs!B27*Inputs!B29)*(1-Inputs!B30)))/((Inputs!B7+((Inputs!B16*(1+0.25)*Inputs!B15)*(1-0.6)/Inputs!B8))*100))-(Inputs!B6/(Inputs!B7*100)))/(Inputs!B6/(Inputs!B7*100)) -> -0.091610275 | J9: =(((Inputs!B6+Inputs!B14+(Inputs!B34*Inputs!B35*(1-Inputs!B30))-(((Inputs!B16*(1+0.25)*Inputs!B15)*0.7*Inputs!B26*Inputs!B28+(Inputs!B16*(1+0.25)*Inputs!B15)*0.7*Inputs!B27*Inputs!B29)*(1-Inputs!B30)))/((Inputs!B7+((Inputs!B16*(1+0.25)*Inputs!B15)*(1-0.7)/Inputs!B8))*100))-(Inputs!B6/(Inputs!B7*100)))/(Inputs!B6/(Inputs!B7*100)) -> -0.095560792 | K9: =(((Inputs!B6+Inputs!B14+(Inputs!B34*Inputs!B35*(1-Inputs!B30))-(((Inputs!B16*(1+0.25)*Inputs!B15)*0.8*Inputs!B26*Inputs!B28+(Inputs!B16*(1+0.25)*Inputs!B15)*0.8*Inputs!B27*Inputs!B29)*(1-Inputs!B30)))/((Inputs!B7+((Inputs!B16*(1+0.25)*Inputs!B15)*(1-0.8)/Inputs!B8))*100))-(Inputs!B6/(Inputs!B7*100)))/(Inputs!B6/(Inputs!B7*100)) -> -0.09964918 | L9: =(((Inputs!B6+Inputs!B14+(Inputs!B34*Inputs!B35*(1-Inputs!B30))-(((Inputs!B16*(1+0.25)*Inputs!B15)*0.9*Inputs!B26*Inputs!B28+(Inputs!B16*(1+0.25)*Inputs!B15)*0.9*Inputs!B27*Inputs!B29)*(1-Inputs!B30)))/((Inputs!B7+((Inputs!B16*(1+0.25)*Inputs!B15)*(1-0.9)/Inputs!B8))*100))-(Inputs!B6/(Inputs!B7*100)))/(Inputs!B6/(Inputs!B7*100)) -> -0.10388278 | M9: =(((Inputs!B6+Inputs!B14+(Inputs!B34*Inputs!B35*(1-Inputs!B30))-(((Inputs!B16*(1+0.25)*Inputs!B15)*1*Inputs!B26*Inputs!B28+(Inputs!B16*(1+0.25)*Inputs!B15)*1*Inputs!B27*Inputs!B29)*(1-Inputs!B30)))/((Inputs!B7+((Inputs!B16*(1+0.25)*Inputs!B15)*(1-1)/Inputs!B8))*100))-(Inputs!B6/(Inputs!B7*100)))/(Inputs!B6/(Inputs!B7*100)) -> -0.10826948
B10: 0.3 | C10: =(((Inputs!B6+Inputs!B14+(Inputs!B34*Inputs!B35*(1-Inputs!B30))-(((Inputs!B16*(1+0.3)*Inputs!B15)*0*Inputs!B26*Inputs!B28+(Inputs!B16*(1+0.3)*Inputs!B15)*0*Inputs!B27*Inputs!B29)*(1-Inputs!B30)))/((Inputs!B7+((Inputs!B16*(1+0.3)*Inputs!B15)*(1-0)/Inputs!B8))*100))-(Inputs!B6/(Inputs!B7*100)))/(Inputs!B6/(Inputs!B7*100)) -> -0.076106535 | D10: =(((Inputs!B6+Inputs!B14+(Inputs!B34*Inputs!B35*(1-Inputs!B30))-(((Inputs!B16*(1+0.3)*Inputs!B15)*0.1*Inputs!B26*Inputs!B28+(Inputs!B16*(1+0.3)*Inputs!B15)*0.1*Inputs!B27*Inputs!B29)*(1-Inputs!B30)))/((Inputs!B7+((Inputs!B16*(1+0.3)*Inputs!B15)*(1-0.1)/Inputs!B8))*100))-(Inputs!B6/(Inputs!B7*100)))/(Inputs!B6/(Inputs!B7*100)) -> -0.079561665 | E10: =(((Inputs!B6+Inputs!B14+(Inputs!B34*Inputs!B35*(1-Inputs!B30))-(((Inputs!B16*(1+0.3)*Inputs!B15)*0.2*Inputs!B26*Inputs!B28+(Inputs!B16*(1+0.3)*Inputs!B15)*0.2*Inputs!B27*Inputs!B29)*(1-Inputs!B30)))/((Inputs!B7+((Inputs!B16*(1+0.3)*Inputs!B15)*(1-0.2)/Inputs!B8))*100))-(Inputs!B6/(Inputs!B7*100)))/(Inputs!B6/(Inputs!B7*100)) -> -0.083129744 | F10: =(((Inputs!B6+Inputs!B14+(Inputs!B34*Inputs!B35*(1-Inputs!B30))-(((Inputs!B16*(1+0.3)*Inputs!B15)*0.3*Inputs!B26*Inputs!B28+(Inputs!B16*(1+0.3)*Inputs!B15)*0.3*Inputs!B27*Inputs!B29)*(1-Inputs!B30)))/((Inputs!B7+((Inputs!B16*(1+0.3)*Inputs!B15)*(1-0.3)/Inputs!B8))*100))-(Inputs!B6/(Inputs!B7*100)))/(Inputs!B6/(Inputs!B7*100)) -> -0.086816403 | G10: =(((Inputs!B6+Inputs!B14+(Inputs!B34*Inputs!B35*(1-Inputs!B30))-(((Inputs!B16*(1+0.3)*Inputs!B15)*0.4*Inputs!B26*Inputs!B28+(Inputs!B16*(1+0.3)*Inputs!B15)*0.4*Inputs!B27*Inputs!B29)*(1-Inputs!B30)))/((Inputs!B7+((Inputs!B16*(1+0.3)*Inputs!B15)*(1-0.4)/Inputs!B8))*100))-(Inputs!B6/(Inputs!B7*100)))/(Inputs!B6/(Inputs!B7*100)) -> -0.090627653 | H10: =(((Inputs!B6+Inputs!B14+(Inputs!B34*Inputs!B35*(1-Inputs!B30))-(((Inputs!B16*(1+0.3)*Inputs!B15)*0.5*Inputs!B26*Inputs!B28+(Inputs!B16*(1+0.3)*Inputs!B15)*0.5*Inputs!B27*Inputs!B29)*(1-Inputs!B30)))/((Inputs!B7+((Inputs!B16*(1+0.3)*Inputs!B15)*(1-0.5)/Inputs!B8))*100))-(Inputs!B6/(Inputs!B7*100)))/(Inputs!B6/(Inputs!B7*100)) -> -0.094569918 | I10: =(((Inputs!B6+Inputs!B14+(Inputs!B34*Inputs!B35*(1-Inputs!B30))-(((Inputs!B16*(1+0.3)*Inputs!B15)*0.6*Inputs!B26*Inputs!B28+(Inputs!B16*(1+0.3)*Inputs!B15)*0.6*Inputs!B27*Inputs!B29)*(1-Inputs!B30)))/((Inputs!B7+((Inputs!B16*(1+0.3)*Inputs!B15)*(1-0.6)/Inputs!B8))*100))-(Inputs!B6/(Inputs!B7*100)))/(Inputs!B6/(Inputs!B7*100)) -> -0.098650073 | J10: =(((Inputs!B6+Inputs!B14+(Inputs!B34*Inputs!B35*(1-Inputs!B30))-(((Inputs!B16*(1+0.3)*Inputs!B15)*0.7*Inputs!B26*Inputs!B28+(Inputs!B16*(1+0.3)*Inputs!B15)*0.7*Inputs!B27*Inputs!B29)*(1-Inputs!B30)))/((Inputs!B7+((Inputs!B16*(1+0.3)*Inputs!B15)*(1-0.7)/Inputs!B8))*100))-(Inputs!B6/(Inputs!B7*100)))/(Inputs!B6/(Inputs!B7*100)) -> -0.10287548 | K10: =(((Inputs!B6+Inputs!B14+(Inputs!B34*Inputs!B35*(1-Inputs!B30))-(((Inputs!B16*(1+0.3)*Inputs!B15)*0.8*Inputs!B26*Inputs!B28+(Inputs!B16*(1+0.3)*Inputs!B15)*0.8*Inputs!B27*Inputs!B29)*(1-Inputs!B30)))/((Inputs!B7+((Inputs!B16*(1+0.3)*Inputs!B15)*(1-0.8)/Inputs!B8))*100))-(Inputs!B6/(Inputs!B7*100)))/(Inputs!B6/(Inputs!B7*100)) -> -0.10725404 | L10: =(((Inputs!B6+Inputs!B14+(Inputs!B34*Inputs!B35*(1-Inputs!B30))-(((Inputs!B16*(1+0.3)*Inputs!B15)*0.9*Inputs!B26*Inputs!B28+(Inputs!B16*(1+0.3)*Inputs!B15)*0.9*Inputs!B27*Inputs!B29)*(1-Inputs!B30)))/((Inputs!B7+((Inputs!B16*(1+0.3)*Inputs!B15)*(1-0.9)/Inputs!B8))*100))-(Inputs!B6/(Inputs!B7*100)))/(Inputs!B6/(Inputs!B7*100)) -> -0.11179422 | M10: =(((Inputs!B6+Inputs!B14+(Inputs!B34*Inputs!B35*(1-Inputs!B30))-(((Inputs!B16*(1+0.3)*Inputs!B15)*1*Inputs!B26*Inputs!B28+(Inputs!B16*(1+0.3)*Inputs!B15)*1*Inputs!B27*Inputs!B29)*(1-Inputs!B30)))/((Inputs!B7+((Inputs!B16*(1+0.3)*Inputs!B15)*(1-1)/Inputs!B8))*100))-(Inputs!B6/(Inputs!B7*100)))/(Inputs!B6/(Inputs!B7*100)) -> -0.11650515
B11: 0.35 | C11: =(((Inputs!B6+Inputs!B14+(Inputs!B34*Inputs!B35*(1-Inputs!B30))-(((Inputs!B16*(1+0.35)*Inputs!B15)*0*Inputs!B26*Inputs!B28+(Inputs!B16*(1+0.35)*Inputs!B15)*0*Inputs!B27*Inputs!B29)*(1-Inputs!B30)))/((Inputs!B7+((Inputs!B16*(1+0.35)*Inputs!B15)*(1-0)/Inputs!B8))*100))-(Inputs!B6/(Inputs!B7*100)))/(Inputs!B6/(Inputs!B7*100)) -> -0.081696791 | D11: =(((Inputs!B6+Inputs!B14+(Inputs!B34*Inputs!B35*(1-Inputs!B30))-(((Inputs!B16*(1+0.35)*Inputs!B15)*0.1*Inputs!B26*Inputs!B28+(Inputs!B16*(1+0.35)*Inputs!B15)*0.1*Inputs!B27*Inputs!B29)*(1-Inputs!B30)))/((Inputs!B7+((Inputs!B16*(1+0.35)*Inputs!B15)*(1-0.1)/Inputs!B8))*100))-(Inputs!B6/(Inputs!B7*100)))/(Inputs!B6/(Inputs!B7*100)) -> -0.085357792 | E11: =(((Inputs!B6+Inputs!B14+(Inputs!B34*Inputs!B35*(1-Inputs!B30))-(((Inputs!B16*(1+0.35)*Inputs!B15)*0.2*Inputs!B26*Inputs!B28+(Inputs!B16*(1+0.35)*Inputs!B15)*0.2*Inputs!B27*Inputs!B29)*(1-Inputs!B30)))/((Inputs!B7+((Inputs!B16*(1+0.35)*Inputs!B15)*(1-0.2)/Inputs!B8))*100))-(Inputs!B6/(Inputs!B7*100)))/(Inputs!B6/(Inputs!B7*100)) -> -0.089142454 | F11: =(((Inputs!B6+Inputs!B14+(Inputs!B34*Inputs!B35*(1-Inputs!B30))-(((Inputs!B16*(1+0.35)*Inputs!B15)*0.3*Inputs!B26*Inputs!B28+(Inputs!B16*(1+0.35)*Inputs!B15)*0.3*Inputs!B27*Inputs!B29)*(1-Inputs!B30)))/((Inputs!B7+((Inputs!B16*(1+0.35)*Inputs!B15)*(1-0.3)/Inputs!B8))*100))-(Inputs!B6/(Inputs!B7*100)))/(Inputs!B6/(Inputs!B7*100)) -> -0.093057148 | G11: =(((Inputs!B6+Inputs!B14+(Inputs!B34*Inputs!B35*(1-Inputs!B30))-(((Inputs!B16*(1+0.35)*Inputs!B15)*0.4*Inputs!B26*Inputs!B28+(Inputs!B16*(1+0.35)*Inputs!B15)*0.4*Inputs!B27*Inputs!B29)*(1-Inputs!B30)))/((Inputs!B7+((Inputs!B16*(1+0.35)*Inputs!B15)*(1-0.4)/Inputs!B8))*100))-(Inputs!B6/(Inputs!B7*100)))/(Inputs!B6/(Inputs!B7*100)) -> -0.097108695 | H11: =(((Inputs!B6+Inputs!B14+(Inputs!B34*Inputs!B35*(1-Inputs!B30))-(((Inputs!B16*(1+0.35)*Inputs!B15)*0.5*Inputs!B26*Inputs!B28+(Inputs!B16*(1+0.35)*Inputs!B15)*0.5*Inputs!B27*Inputs!B29)*(1-Inputs!B30)))/((Inputs!B7+((Inputs!B16*(1+0.35)*Inputs!B15)*(1-0.5)/Inputs!B8))*100))-(Inputs!B6/(Inputs!B7*100)))/(Inputs!B6/(Inputs!B7*100)) -> -0.1013044 | I11: =(((Inputs!B6+Inputs!B14+(Inputs!B34*Inputs!B35*(1-Inputs!B30))-(((Inputs!B16*(1+0.35)*Inputs!B15)*0.6*Inputs!B26*Inputs!B28+(Inputs!B16*(1+0.35)*Inputs!B15)*0.6*Inputs!B27*Inputs!B29)*(1-Inputs!B30)))/((Inputs!B7+((Inputs!B16*(1+0.35)*Inputs!B15)*(1-0.6)/Inputs!B8))*100))-(Inputs!B6/(Inputs!B7*100)))/(Inputs!B6/(Inputs!B7*100)) -> -0.10565209 | J11: =(((Inputs!B6+Inputs!B14+(Inputs!B34*Inputs!B35*(1-Inputs!B30))-(((Inputs!B16*(1+0.35)*Inputs!B15)*0.7*Inputs!B26*Inputs!B28+(Inputs!B16*(1+0.35)*Inputs!B15)*0.7*Inputs!B27*Inputs!B29)*(1-Inputs!B30)))/((Inputs!B7+((Inputs!B16*(1+0.35)*Inputs!B15)*(1-0.7)/Inputs!B8))*100))-(Inputs!B6/(Inputs!B7*100)))/(Inputs!B6/(Inputs!B7*100)) -> -0.11016018 | K11: =(((Inputs!B6+Inputs!B14+(Inputs!B34*Inputs!B35*(1-Inputs!B30))-(((Inputs!B16*(1+0.35)*Inputs!B15)*0.8*Inputs!B26*Inputs!B28+(Inputs!B16*(1+0.35)*Inputs!B15)*0.8*Inputs!B27*Inputs!B29)*(1-Inputs!B30)))/((Inputs!B7+((Inputs!B16*(1+0.35)*Inputs!B15)*(1-0.8)/Inputs!B8))*100))-(Inputs!B6/(Inputs!B7*100)))/(Inputs!B6/(Inputs!B7*100)) -> -0.11483772 | L11: =(((Inputs!B6+Inputs!B14+(Inputs!B34*Inputs!B35*(1-Inputs!B30))-(((Inputs!B16*(1+0.35)*Inputs!B15)*0.9*Inputs!B26*Inputs!B28+(Inputs!B16*(1+0.35)*Inputs!B15)*0.9*Inputs!B27*Inputs!B29)*(1-Inputs!B30)))/((Inputs!B7+((Inputs!B16*(1+0.35)*Inputs!B15)*(1-0.9)/Inputs!B8))*100))-(Inputs!B6/(Inputs!B7*100)))/(Inputs!B6/(Inputs!B7*100)) -> -0.11969443 | M11: =(((Inputs!B6+Inputs!B14+(Inputs!B34*Inputs!B35*(1-Inputs!B30))-(((Inputs!B16*(1+0.35)*Inputs!B15)*1*Inputs!B26*Inputs!B28+(Inputs!B16*(1+0.35)*Inputs!B15)*1*Inputs!B27*Inputs!B29)*(1-Inputs!B30)))/((Inputs!B7+((Inputs!B16*(1+0.35)*Inputs!B15)*(1-1)/Inputs!B8))*100))-(Inputs!B6/(Inputs!B7*100)))/(Inputs!B6/(Inputs!B7*100)) -> -0.12474083
B12: 0.4 | C12: =(((Inputs!B6+Inputs!B14+(Inputs!B34*Inputs!B35*(1-Inputs!B30))-(((Inputs!B16*(1+0.4)*Inputs!B15)*0*Inputs!B26*Inputs!B28+(Inputs!B16*(1+0.4)*Inputs!B15)*0*Inputs!B27*Inputs!B29)*(1-Inputs!B30)))/((Inputs!B7+((Inputs!B16*(1+0.4)*Inputs!B15)*(1-0)/Inputs!B8))*100))-(Inputs!B6/(Inputs!B7*100)))/(Inputs!B6/(Inputs!B7*100)) -> -0.087219804 | D12: =(((Inputs!B6+Inputs!B14+(Inputs!B34*Inputs!B35*(1-Inputs!B30))-(((Inputs!B16*(1+0.4)*Inputs!B15)*0.1*Inputs!B26*Inputs!B28+(Inputs!B16*(1+0.4)*Inputs!B15)*0.1*Inputs!B27*Inputs!B29)*(1-Inputs!B30)))/((Inputs!B7+((Inputs!B16*(1+0.4)*Inputs!B15)*(1-0.1)/Inputs!B8))*100))-(Inputs!B6/(Inputs!B7*100)))/(Inputs!B6/(Inputs!B7*100)) -> -0.091090097 | E12: =(((Inputs!B6+Inputs!B14+(Inputs!B34*Inputs!B35*(1-Inputs!B30))-(((Inputs!B16*(1+0.4)*Inputs!B15)*0.2*Inputs!B26*Inputs!B28+(Inputs!B16*(1+0.4)*Inputs!B15)*0.2*Inputs!B27*Inputs!B29)*(1-Inputs!B30)))/((Inputs!B7+((Inputs!B16*(1+0.4)*Inputs!B15)*(1-0.2)/Inputs!B8))*100))-(Inputs!B6/(Inputs!B7*100)))/(Inputs!B6/(Inputs!B7*100)) -> -0.095095286 | F12: =(((Inputs!B6+Inputs!B14+(Inputs!B34*Inputs!B35*(1-Inputs!B30))-(((Inputs!B16*(1+0.4)*Inputs!B15)*0.3*Inputs!B26*Inputs!B28+(Inputs!B16*(1+0.4)*Inputs!B15)*0.3*Inputs!B27*Inputs!B29)*(1-Inputs!B30)))/((Inputs!B7+((Inputs!B16*(1+0.4)*Inputs!B15)*(1-0.3)/Inputs!B8))*100))-(Inputs!B6/(Inputs!B7*100)))/(Inputs!B6/(Inputs!B7*100)) -> -0.09924255 | G12: =(((Inputs!B6+Inputs!B14+(Inputs!B34*Inputs!B35*(1-Inputs!B30))-(((Inputs!B16*(1+0.4)*Inputs!B15)*0.4*Inputs!B26*Inputs!B28+(Inputs!B16*(1+0.4)*Inputs!B15)*0.4*Inputs!B27*Inputs!B29)*(1-Inputs!B30)))/((Inputs!B7+((Inputs!B16*(1+0.4)*Inputs!B15)*(1-0.4)/Inputs!B8))*100))-(Inputs!B6/(Inputs!B7*100)))/(Inputs!B6/(Inputs!B7*100)) -> -0.10353958 | H12: =(((Inputs!B6+Inputs!B14+(Inputs!B34*Inputs!B35*(1-Inputs!B30))-(((Inputs!B16*(1+0.4)*Inputs!B15)*0.5*Inputs!B26*Inputs!B28+(Inputs!B16*(1+0.4)*Inputs!B15)*0.5*Inputs!B27*Inputs!B29)*(1-Inputs!B30)))/((Inputs!B7+((Inputs!B16*(1+0.4)*Inputs!B15)*(1-0.5)/Inputs!B8))*100))-(Inputs!B6/(Inputs!B7*100)))/(Inputs!B6/(Inputs!B7*100)) -> -0.10799465 | I12: =(((Inputs!B6+Inputs!B14+(Inputs!B34*Inputs!B35*(1-Inputs!B30))-(((Inputs!B16*(1+0.4)*Inputs!B15)*0.6*Inputs!B26*Inputs!B28+(Inputs!B16*(1+0.4)*Inputs!B15)*0.6*Inputs!B27*Inputs!B29)*(1-Inputs!B30)))/((Inputs!B7+((Inputs!B16*(1+0.4)*Inputs!B15)*(1-0.6)/Inputs!B8))*100))-(Inputs!B6/(Inputs!B7*100)))/(Inputs!B6/(Inputs!B7*100)) -> -0.11261663 | J12: =(((Inputs!B6+Inputs!B14+(Inputs!B34*Inputs!B35*(1-Inputs!B30))-(((Inputs!B16*(1+0.4)*Inputs!B15)*0.7*Inputs!B26*Inputs!B28+(Inputs!B16*(1+0.4)*Inputs!B15)*0.7*Inputs!B27*Inputs!B29)*(1-Inputs!B30)))/((Inputs!B7+((Inputs!B16*(1+0.4)*Inputs!B15)*(1-0.7)/Inputs!B8))*100))-(Inputs!B6/(Inputs!B7*100)))/(Inputs!B6/(Inputs!B7*100)) -> -0.11741509 | K12: =(((Inputs!B6+Inputs!B14+(Inputs!B34*Inputs!B35*(1-Inputs!B30))-(((Inputs!B16*(1+0.4)*Inputs!B15)*0.8*Inputs!B26*Inputs!B28+(Inputs!B16*(1+0.4)*Inputs!B15)*0.8*Inputs!B27*Inputs!B29)*(1-Inputs!B30)))/((Inputs!B7+((Inputs!B16*(1+0.4)*Inputs!B15)*(1-0.8)/Inputs!B8))*100))-(Inputs!B6/(Inputs!B7*100)))/(Inputs!B6/(Inputs!B7*100)) -> -0.12240032 | L12: =(((Inputs!B6+Inputs!B14+(Inputs!B34*Inputs!B35*(1-Inputs!B30))-(((Inputs!B16*(1+0.4)*Inputs!B15)*0.9*Inputs!B26*Inputs!B28+(Inputs!B16*(1+0.4)*Inputs!B15)*0.9*Inputs!B27*Inputs!B29)*(1-Inputs!B30)))/((Inputs!B7+((Inputs!B16*(1+0.4)*Inputs!B15)*(1-0.9)/Inputs!B8))*100))-(Inputs!B6/(Inputs!B7*100)))/(Inputs!B6/(Inputs!B7*100)) -> -0.12758345 | M12: =(((Inputs!B6+Inputs!B14+(Inputs!B34*Inputs!B35*(1-Inputs!B30))-(((Inputs!B16*(1+0.4)*Inputs!B15)*1*Inputs!B26*Inputs!B28+(Inputs!B16*(1+0.4)*Inputs!B15)*1*Inputs!B27*Inputs!B29)*(1-Inputs!B30)))/((Inputs!B7+((Inputs!B16*(1+0.4)*Inputs!B15)*(1-1)/Inputs!B8))*100))-(Inputs!B6/(Inputs!B7*100)))/(Inputs!B6/(Inputs!B7*100)) -> -0.1329765
B13: 0.45 | C13: =(((Inputs!B6+Inputs!B14+(Inputs!B34*Inputs!B35*(1-Inputs!B30))-(((Inputs!B16*(1+0.45)*Inputs!B15)*0*Inputs!B26*Inputs!B28+(Inputs!B16*(1+0.45)*Inputs!B15)*0*Inputs!B27*Inputs!B29)*(1-Inputs!B30)))/((Inputs!B7+((Inputs!B16*(1+0.45)*Inputs!B15)*(1-0)/Inputs!B8))*100))-(Inputs!B6/(Inputs!B7*100)))/(Inputs!B6/(Inputs!B7*100)) -> -0.09267678 | D13: =(((Inputs!B6+Inputs!B14+(Inputs!B34*Inputs!B35*(1-Inputs!B30))-(((Inputs!B16*(1+0.45)*Inputs!B15)*0.1*Inputs!B26*Inputs!B28+(Inputs!B16*(1+0.45)*Inputs!B15)*0.1*Inputs!B27*Inputs!B29)*(1-Inputs!B30)))/((Inputs!B7+((Inputs!B16*(1+0.45)*Inputs!B15)*(1-0.1)/Inputs!B8))*100))-(Inputs!B6/(Inputs!B7*100)))/(Inputs!B6/(Inputs!B7*100)) -> -0.096759627 | E13: =(((Inputs!B6+Inputs!B14+(Inputs!B34*Inputs!B35*(1-Inputs!B30))-(((Inputs!B16*(1+0.45)*Inputs!B15)*0.2*Inputs!B26*Inputs!B28+(Inputs!B16*(1+0.45)*Inputs!B15)*0.2*Inputs!B27*Inputs!B29)*(1-Inputs!B30)))/((Inputs!B7+((Inputs!B16*(1+0.45)*Inputs!B15)*(1-0.2)/Inputs!B8))*100))-(Inputs!B6/(Inputs!B7*100)))/(Inputs!B6/(Inputs!B7*100)) -> -0.10098913 | F13: =(((Inputs!B6+Inputs!B14+(Inputs!B34*Inputs!B35*(1-Inputs!B30))-(((Inputs!B16*(1+0.45)*Inputs!B15)*0.3*Inputs!B26*Inputs!B28+(Inputs!B16*(1+0.45)*Inputs!B15)*0.3*Inputs!B27*Inputs!B29)*(1-Inputs!B30)))/((Inputs!B7+((Inputs!B16*(1+0.45)*Inputs!B15)*(1-0.3)/Inputs!B8))*100))-(Inputs!B6/(Inputs!B7*100)))/(Inputs!B6/(Inputs!B7*100)) -> -0.10537334 | G13: =(((Inputs!B6+Inputs!B14+(Inputs!B34*Inputs!B35*(1-Inputs!B30))-(((Inputs!B16*(1+0.45)*Inputs!B15)*0.4*Inputs!B26*Inputs!B28+(Inputs!B16*(1+0.45)*Inputs!B15)*0.4*Inputs!B27*Inputs!B29)*(1-Inputs!B30)))/((Inputs!B7+((Inputs!B16*(1+0.45)*Inputs!B15)*(1-0.4)/Inputs!B8))*100))-(Inputs!B6/(Inputs!B7*100)))/(Inputs!B6/(Inputs!B7*100)) -> -0.1099209 | H13: =(((Inputs!B6+Inputs!B14+(Inputs!B34*Inputs!B35*(1-Inputs!B30))-(((Inputs!B16*(1+0.45)*Inputs!B15)*0.5*Inputs!B26*Inputs!B28+(Inputs!B16*(1+0.45)*Inputs!B15)*0.5*Inputs!B27*Inputs!B29)*(1-Inputs!B30)))/((Inputs!B7+((Inputs!B16*(1+0.45)*Inputs!B15)*(1-0.5)/Inputs!B8))*100))-(Inputs!B6/(Inputs!B7*100)))/(Inputs!B6/(Inputs!B7*100)) -> -0.11464111 | I13: =(((Inputs!B6+Inputs!B14+(Inputs!B34*Inputs!B35*(1-Inputs!B30))-(((Inputs!B16*(1+0.45)*Inputs!B15)*0.6*Inputs!B26*Inputs!B28+(Inputs!B16*(1+0.45)*Inputs!B15)*0.6*Inputs!B27*Inputs!B29)*(1-Inputs!B30)))/((Inputs!B7+((Inputs!B16*(1+0.45)*Inputs!B15)*(1-0.6)/Inputs!B8))*100))-(Inputs!B6/(Inputs!B7*100)))/(Inputs!B6/(Inputs!B7*100)) -> -0.119544 | J13: =(((Inputs!B6+Inputs!B14+(Inputs!B34*Inputs!B35*(1-Inputs!B30))-(((Inputs!B16*(1+0.45)*Inputs!B15)*0.7*Inputs!B26*Inputs!B28+(Inputs!B16*(1+0.45)*Inputs!B15)*0.7*Inputs!B27*Inputs!B29)*(1-Inputs!B30)))/((Inputs!B7+((Inputs!B16*(1+0.45)*Inputs!B15)*(1-0.7)/Inputs!B8))*100))-(Inputs!B6/(Inputs!B7*100)))/(Inputs!B6/(Inputs!B7*100)) -> -0.12464037 | K13: =(((Inputs!B6+Inputs!B14+(Inputs!B34*Inputs!B35*(1-Inputs!B30))-(((Inputs!B16*(1+0.45)*Inputs!B15)*0.8*Inputs!B26*Inputs!B28+(Inputs!B16*(1+0.45)*Inputs!B15)*0.8*Inputs!B27*Inputs!B29)*(1-Inputs!B30)))/((Inputs!B7+((Inputs!B16*(1+0.45)*Inputs!B15)*(1-0.8)/Inputs!B8))*100))-(Inputs!B6/(Inputs!B7*100)))/(Inputs!B6/(Inputs!B7*100)) -> -0.12994192 | L13: =(((Inputs!B6+Inputs!B14+(Inputs!B34*Inputs!B35*(1-Inputs!B30))-(((Inputs!B16*(1+0.45)*Inputs!B15)*0.9*Inputs!B26*Inputs!B28+(Inputs!B16*(1+0.45)*Inputs!B15)*0.9*Inputs!B27*Inputs!B29)*(1-Inputs!B30)))/((Inputs!B7+((Inputs!B16*(1+0.45)*Inputs!B15)*(1-0.9)/Inputs!B8))*100))-(Inputs!B6/(Inputs!B7*100)))/(Inputs!B6/(Inputs!B7*100)) -> -0.13546128 | M13: =(((Inputs!B6+Inputs!B14+(Inputs!B34*Inputs!B35*(1-Inputs!B30))-(((Inputs!B16*(1+0.45)*Inputs!B15)*1*Inputs!B26*Inputs!B28+(Inputs!B16*(1+0.45)*Inputs!B15)*1*Inputs!B27*Inputs!B29)*(1-Inputs!B30)))/((Inputs!B7+((Inputs!B16*(1+0.45)*Inputs!B15)*(1-1)/Inputs!B8))*100))-(Inputs!B6/(Inputs!B7*100)))/(Inputs!B6/(Inputs!B7*100)) -> -0.14121217
B15: TABLE 2 — YEAR 3 ACCRETION / (DILUTION) % (synergy ramp 70% of run-rate)
B16: Row input: Offer Premium | Column input: % Cash Consideration | Formula independent — no Excel Data Table engine required
B17: Premium ↓ / Cash % → | C17: 0 | D17: 0.1 | E17: 0.2 | F17: 0.3 | G17: 0.4 | H17: 0.5 | I17: 0.6 | J17: 0.7 | K17: 0.8 | L17: 0.9 | M17: 1
B18: 0.15 | C18: =(((Inputs!B6+Inputs!B14+(Inputs!B34*Inputs!B37*(1-Inputs!B30))-(((Inputs!B16*(1+0.15)*Inputs!B15)*0*Inputs!B26*Inputs!B28+(Inputs!B16*(1+0.15)*Inputs!B15)*0*Inputs!B27*Inputs!B29)*(1-Inputs!B30)))/((Inputs!B7+((Inputs!B16*(1+0.15)*Inputs!B15)*(1-0)/Inputs!B8))*100))-(Inputs!B6/(Inputs!B7*100)))/(Inputs!B6/(Inputs!B7*100)) -> -0.018671485 | D18: =(((Inputs!B6+Inputs!B14+(Inputs!B34*Inputs!B37*(1-Inputs!B30))-(((Inputs!B16*(1+0.15)*Inputs!B15)*0.1*Inputs!B26*Inputs!B28+(Inputs!B16*(1+0.15)*Inputs!B15)*0.1*Inputs!B27*Inputs!B29)*(1-Inputs!B30)))/((Inputs!B7+((Inputs!B16*(1+0.15)*Inputs!B15)*(1-0.1)/Inputs!B8))*100))-(Inputs!B6/(Inputs!B7*100)))/(Inputs!B6/(Inputs!B7*100)) -> -0.020948872 | E18: =(((Inputs!B6+Inputs!B14+(Inputs!B34*Inputs!B37*(1-Inputs!B30))-(((Inputs!B16*(1+0.15)*Inputs!B15)*0.2*Inputs!B26*Inputs!B28+(Inputs!B16*(1+0.15)*Inputs!B15)*0.2*Inputs!B27*Inputs!B29)*(1-Inputs!B30)))/((Inputs!B7+((Inputs!B16*(1+0.15)*Inputs!B15)*(1-0.2)/Inputs!B8))*100))-(Inputs!B6/(Inputs!B7*100)))/(Inputs!B6/(Inputs!B7*100)) -> -0.023293127 | F18: =(((Inputs!B6+Inputs!B14+(Inputs!B34*Inputs!B37*(1-Inputs!B30))-(((Inputs!B16*(1+0.15)*Inputs!B15)*0.3*Inputs!B26*Inputs!B28+(Inputs!B16*(1+0.15)*Inputs!B15)*0.3*Inputs!B27*Inputs!B29)*(1-Inputs!B30)))/((Inputs!B7+((Inputs!B16*(1+0.15)*Inputs!B15)*(1-0.3)/Inputs!B8))*100))-(Inputs!B6/(Inputs!B7*100)))/(Inputs!B6/(Inputs!B7*100)) -> -0.025707238 | G18: =(((Inputs!B6+Inputs!B14+(Inputs!B34*Inputs!B37*(1-Inputs!B30))-(((Inputs!B16*(1+0.15)*Inputs!B15)*0.4*Inputs!B26*Inputs!B28+(Inputs!B16*(1+0.15)*Inputs!B15)*0.4*Inputs!B27*Inputs!B29)*(1-Inputs!B30)))/((Inputs!B7+((Inputs!B16*(1+0.15)*Inputs!B15)*(1-0.4)/Inputs!B8))*100))-(Inputs!B6/(Inputs!B7*100)))/(Inputs!B6/(Inputs!B7*100)) -> -0.028194374 | H18: =(((Inputs!B6+Inputs!B14+(Inputs!B34*Inputs!B37*(1-Inputs!B30))-(((Inputs!B16*(1+0.15)*Inputs!B15)*0.5*Inputs!B26*Inputs!B28+(Inputs!B16*(1+0.15)*Inputs!B15)*0.5*Inputs!B27*Inputs!B29)*(1-Inputs!B30)))/((Inputs!B7+((Inputs!B16*(1+0.15)*Inputs!B15)*(1-0.5)/Inputs!B8))*100))-(Inputs!B6/(Inputs!B7*100)))/(Inputs!B6/(Inputs!B7*100)) -> -0.030757901 | I18: =(((Inputs!B6+Inputs!B14+(Inputs!B34*Inputs!B37*(1-Inputs!B30))-(((Inputs!B16*(1+0.15)*Inputs!B15)*0.6*Inputs!B26*Inputs!B28+(Inputs!B16*(1+0.15)*Inputs!B15)*0.6*Inputs!B27*Inputs!B29)*(1-Inputs!B30)))/((Inputs!B7+((Inputs!B16*(1+0.15)*Inputs!B15)*(1-0.6)/Inputs!B8))*100))-(Inputs!B6/(Inputs!B7*100)))/(Inputs!B6/(Inputs!B7*100)) -> -0.033401392 | J18: =(((Inputs!B6+Inputs!B14+(Inputs!B34*Inputs!B37*(1-Inputs!B30))-(((Inputs!B16*(1+0.15)*Inputs!B15)*0.7*Inputs!B26*Inputs!B28+(Inputs!B16*(1+0.15)*Inputs!B15)*0.7*Inputs!B27*Inputs!B29)*(1-Inputs!B30)))/((Inputs!B7+((Inputs!B16*(1+0.15)*Inputs!B15)*(1-0.7)/Inputs!B8))*100))-(Inputs!B6/(Inputs!B7*100)))/(Inputs!B6/(Inputs!B7*100)) -> -0.036128648 | K18: =(((Inputs!B6+Inputs!B14+(Inputs!B34*Inputs!B37*(1-Inputs!B30))-(((Inputs!B16*(1+0.15)*Inputs!B15)*0.8*Inputs!B26*Inputs!B28+(Inputs!B16*(1+0.15)*Inputs!B15)*0.8*Inputs!B27*Inputs!B29)*(1-Inputs!B30)))/((Inputs!B7+((Inputs!B16*(1+0.15)*Inputs!B15)*(1-0.8)/Inputs!B8))*100))-(Inputs!B6/(Inputs!B7*100)))/(Inputs!B6/(Inputs!B7*100)) -> -0.038943714 | L18: =(((Inputs!B6+Inputs!B14+(Inputs!B34*Inputs!B37*(1-Inputs!B30))-(((Inputs!B16*(1+0.15)*Inputs!B15)*0.9*Inputs!B26*Inputs!B28+(Inputs!B16*(1+0.15)*Inputs!B15)*0.9*Inputs!B27*Inputs!B29)*(1-Inputs!B30)))/((Inputs!B7+((Inputs!B16*(1+0.15)*Inputs!B15)*(1-0.9)/Inputs!B8))*100))-(Inputs!B6/(Inputs!B7*100)))/(Inputs!B6/(Inputs!B7*100)) -> -0.041850902 | M18: =(((Inputs!B6+Inputs!B14+(Inputs!B34*Inputs!B37*(1-Inputs!B30))-(((Inputs!B16*(1+0.15)*Inputs!B15)*1*Inputs!B26*Inputs!B28+(Inputs!B16*(1+0.15)*Inputs!B15)*1*Inputs!B27*Inputs!B29)*(1-Inputs!B30)))/((Inputs!B7+((Inputs!B16*(1+0.15)*Inputs!B15)*(1-1)/Inputs!B8))*100))-(Inputs!B6/(Inputs!B7*100)))/(Inputs!B6/(Inputs!B7*100)) -> -0.044854807
B19: 0.2 | C19: =(((Inputs!B6+Inputs!B14+(Inputs!B34*Inputs!B37*(1-Inputs!B30))-(((Inputs!B16*(1+0.2)*Inputs!B15)*0*Inputs!B26*Inputs!B28+(Inputs!B16*(1+0.2)*Inputs!B15)*0*Inputs!B27*Inputs!B29)*(1-Inputs!B30)))/((Inputs!B7+((Inputs!B16*(1+0.2)*Inputs!B15)*(1-0)/Inputs!B8))*100))-(Inputs!B6/(Inputs!B7*100)))/(Inputs!B6/(Inputs!B7*100)) -> -0.024719044 | D19: =(((Inputs!B6+Inputs!B14+(Inputs!B34*Inputs!B37*(1-Inputs!B30))-(((Inputs!B16*(1+0.2)*Inputs!B15)*0.1*Inputs!B26*Inputs!B28+(Inputs!B16*(1+0.2)*Inputs!B15)*0.1*Inputs!B27*Inputs!B29)*(1-Inputs!B30)))/((Inputs!B7+((Inputs!B16*(1+0.2)*Inputs!B15)*(1-0.1)/Inputs!B8))*100))-(Inputs!B6/(Inputs!B7*100)))/(Inputs!B6/(Inputs!B7*100)) -> -0.027172858 | E19: =(((Inputs!B6+Inputs!B14+(Inputs!B34*Inputs!B37*(1-Inputs!B30))-(((Inputs!B16*(1+0.2)*Inputs!B15)*0.2*Inputs!B26*Inputs!B28+(Inputs!B16*(1+0.2)*Inputs!B15)*0.2*Inputs!B27*Inputs!B29)*(1-Inputs!B30)))/((Inputs!B7+((Inputs!B16*(1+0.2)*Inputs!B15)*(1-0.2)/Inputs!B8))*100))-(Inputs!B6/(Inputs!B7*100)))/(Inputs!B6/(Inputs!B7*100)) -> -0.02970147 | F19: =(((Inputs!B6+Inputs!B14+(Inputs!B34*Inputs!B37*(1-Inputs!B30))-(((Inputs!B16*(1+0.2)*Inputs!B15)*0.3*Inputs!B26*Inputs!B28+(Inputs!B16*(1+0.2)*Inputs!B15)*0.3*Inputs!B27*Inputs!B29)*(1-Inputs!B30)))/((Inputs!B7+((Inputs!B16*(1+0.2)*Inputs!B15)*(1-0.3)/Inputs!B8))*100))-(Inputs!B6/(Inputs!B7*100)))/(Inputs!B6/(Inputs!B7*100)) -> -0.032308353 | G19: =(((Inputs!B6+Inputs!B14+(Inputs!B34*Inputs!B37*(1-Inputs!B30))-(((Inputs!B16*(1+0.2)*Inputs!B15)*0.4*Inputs!B26*Inputs!B28+(Inputs!B16*(1+0.2)*Inputs!B15)*0.4*Inputs!B27*Inputs!B29)*(1-Inputs!B30)))/((Inputs!B7+((Inputs!B16*(1+0.2)*Inputs!B15)*(1-0.4)/Inputs!B8))*100))-(Inputs!B6/(Inputs!B7*100)))/(Inputs!B6/(Inputs!B7*100)) -> -0.034997198 | H19: =(((Inputs!B6+Inputs!B14+(Inputs!B34*Inputs!B37*(1-Inputs!B30))-(((Inputs!B16*(1+0.2)*Inputs!B15)*0.5*Inputs!B26*Inputs!B28+(Inputs!B16*(1+0.2)*Inputs!B15)*0.5*Inputs!B27*Inputs!B29)*(1-Inputs!B30)))/((Inputs!B7+((Inputs!B16*(1+0.2)*Inputs!B15)*(1-0.5)/Inputs!B8))*100))-(Inputs!B6/(Inputs!B7*100)))/(Inputs!B6/(Inputs!B7*100)) -> -0.037771932 | I19: =(((Inputs!B6+Inputs!B14+(Inputs!B34*Inputs!B37*(1-Inputs!B30))-(((Inputs!B16*(1+0.2)*Inputs!B15)*0.6*Inputs!B26*Inputs!B28+(Inputs!B16*(1+0.2)*Inputs!B15)*0.6*Inputs!B27*Inputs!B29)*(1-Inputs!B30)))/((Inputs!B7+((Inputs!B16*(1+0.2)*Inputs!B15)*(1-0.6)/Inputs!B8))*100))-(Inputs!B6/(Inputs!B7*100)))/(Inputs!B6/(Inputs!B7*100)) -> -0.040636738 | J19: =(((Inputs!B6+Inputs!B14+(Inputs!B34*Inputs!B37*(1-Inputs!B30))-(((Inputs!B16*(1+0.2)*Inputs!B15)*0.7*Inputs!B26*Inputs!B28+(Inputs!B16*(1+0.2)*Inputs!B15)*0.7*Inputs!B27*Inputs!B29)*(1-Inputs!B30)))/((Inputs!B7+((Inputs!B16*(1+0.2)*Inputs!B15)*(1-0.7)/Inputs!B8))*100))-(Inputs!B6/(Inputs!B7*100)))/(Inputs!B6/(Inputs!B7*100)) -> -0.043596073 | K19: =(((Inputs!B6+Inputs!B14+(Inputs!B34*Inputs!B37*(1-Inputs!B30))-(((Inputs!B16*(1+0.2)*Inputs!B15)*0.8*Inputs!B26*Inputs!B28+(Inputs!B16*(1+0.2)*Inputs!B15)*0.8*Inputs!B27*Inputs!B29)*(1-Inputs!B30)))/((Inputs!B7+((Inputs!B16*(1+0.2)*Inputs!B15)*(1-0.8)/Inputs!B8))*100))-(Inputs!B6/(Inputs!B7*100)))/(Inputs!B6/(Inputs!B7*100)) -> -0.046654694 | L19: =(((Inputs!B6+Inputs!B14+(Inputs!B34*Inputs!B37*(1-Inputs!B30))-(((Inputs!B16*(1+0.2)*Inputs!B15)*0.9*Inputs!B26*Inputs!B28+(Inputs!B16*(1+0.2)*Inputs!B15)*0.9*Inputs!B27*Inputs!B29)*(1-Inputs!B30)))/((Inputs!B7+((Inputs!B16*(1+0.2)*Inputs!B15)*(1-0.9)/Inputs!B8))*100))-(Inputs!B6/(Inputs!B7*100)))/(Inputs!B6/(Inputs!B7*100)) -> -0.049817685 | M19: =(((Inputs!B6+Inputs!B14+(Inputs!B34*Inputs!B37*(1-Inputs!B30))-(((Inputs!B16*(1+0.2)*Inputs!B15)*1*Inputs!B26*Inputs!B28+(Inputs!B16*(1+0.2)*Inputs!B15)*1*Inputs!B27*Inputs!B29)*(1-Inputs!B30)))/((Inputs!B7+((Inputs!B16*(1+0.2)*Inputs!B15)*(1-1)/Inputs!B8))*100))-(Inputs!B6/(Inputs!B7*100)))/(Inputs!B6/(Inputs!B7*100)) -> -0.053090479
B20: 0.25 | C20: =(((Inputs!B6+Inputs!B14+(Inputs!B34*Inputs!B37*(1-Inputs!B30))-(((Inputs!B16*(1+0.25)*Inputs!B15)*0*Inputs!B26*Inputs!B28+(Inputs!B16*(1+0.25)*Inputs!B15)*0*Inputs!B27*Inputs!B29)*(1-Inputs!B30)))/((Inputs!B7+((Inputs!B16*(1+0.25)*Inputs!B15)*(1-0)/Inputs!B8))*100))-(Inputs!B6/(Inputs!B7*100)))/(Inputs!B6/(Inputs!B7*100)) -> -0.030692522 | D20: =(((Inputs!B6+Inputs!B14+(Inputs!B34*Inputs!B37*(1-Inputs!B30))-(((Inputs!B16*(1+0.25)*Inputs!B15)*0.1*Inputs!B26*Inputs!B28+(Inputs!B16*(1+0.25)*Inputs!B15)*0.1*Inputs!B27*Inputs!B29)*(1-Inputs!B30)))/((Inputs!B7+((Inputs!B16*(1+0.25)*Inputs!B15)*(1-0.1)/Inputs!B8))*100))-(Inputs!B6/(Inputs!B7*100)))/(Inputs!B6/(Inputs!B7*100)) -> -0.033327159 | E20: =(((Inputs!B6+Inputs!B14+(Inputs!B34*Inputs!B37*(1-Inputs!B30))-(((Inputs!B16*(1+0.25)*Inputs!B15)*0.2*Inputs!B26*Inputs!B28+(Inputs!B16*(1+0.25)*Inputs!B15)*0.2*Inputs!B27*Inputs!B29)*(1-Inputs!B30)))/((Inputs!B7+((Inputs!B16*(1+0.25)*Inputs!B15)*(1-0.2)/Inputs!B8))*100))-(Inputs!B6/(Inputs!B7*100)))/(Inputs!B6/(Inputs!B7*100)) -> -0.036045029 | F20: =(((Inputs!B6+Inputs!B14+(Inputs!B34*Inputs!B37*(1-Inputs!B30))-(((Inputs!B16*(1+0.25)*Inputs!B15)*0.3*Inputs!B26*Inputs!B28+(Inputs!B16*(1+0.25)*Inputs!B15)*0.3*Inputs!B27*Inputs!B29)*(1-Inputs!B30)))/((Inputs!B7+((Inputs!B16*(1+0.25)*Inputs!B15)*(1-0.3)/Inputs!B8))*100))-(Inputs!B6/(Inputs!B7*100)))/(Inputs!B6/(Inputs!B7*100)) -> -0.038850139 | G20: =(((Inputs!B6+Inputs!B14+(Inputs!B34*Inputs!B37*(1-Inputs!B30))-(((Inputs!B16*(1+0.25)*Inputs!B15)*0.4*Inputs!B26*Inputs!B28+(Inputs!B16*(1+0.25)*Inputs!B15)*0.4*Inputs!B27*Inputs!B29)*(1-Inputs!B30)))/((Inputs!B7+((Inputs!B16*(1+0.25)*Inputs!B15)*(1-0.4)/Inputs!B8))*100))-(Inputs!B6/(Inputs!B7*100)))/(Inputs!B6/(Inputs!B7*100)) -> -0.041746759 | H20: =(((Inputs!B6+Inputs!B14+(Inputs!B34*Inputs!B37*(1-Inputs!B30))-(((Inputs!B16*(1+0.25)*Inputs!B15)*0.5*Inputs!B26*Inputs!B28+(Inputs!B16*(1+0.25)*Inputs!B15)*0.5*Inputs!B27*Inputs!B29)*(1-Inputs!B30)))/((Inputs!B7+((Inputs!B16*(1+0.25)*Inputs!B15)*(1-0.5)/Inputs!B8))*100))-(Inputs!B6/(Inputs!B7*100)))/(Inputs!B6/(Inputs!B7*100)) -> -0.044739441 | I20: =(((Inputs!B6+Inputs!B14+(Inputs!B34*Inputs!B37*(1-Inputs!B30))-(((Inputs!B16*(1+0.25)*Inputs!B15)*0.6*Inputs!B26*Inputs!B28+(Inputs!B16*(1+0.25)*Inputs!B15)*0.6*Inputs!B27*Inputs!B29)*(1-Inputs!B30)))/((Inputs!B7+((Inputs!B16*(1+0.25)*Inputs!B15)*(1-0.6)/Inputs!B8))*100))-(Inputs!B6/(Inputs!B7*100)))/(Inputs!B6/(Inputs!B7*100)) -> -0.047833044 | J20: =(((Inputs!B6+Inputs!B14+(Inputs!B34*Inputs!B37*(1-Inputs!B30))-(((Inputs!B16*(1+0.25)*Inputs!B15)*0.7*Inputs!B26*Inputs!B28+(Inputs!B16*(1+0.25)*Inputs!B15)*0.7*Inputs!B27*Inputs!B29)*(1-Inputs!B30)))/((Inputs!B7+((Inputs!B16*(1+0.25)*Inputs!B15)*(1-0.7)/Inputs!B8))*100))-(Inputs!B6/(Inputs!B7*100)))/(Inputs!B6/(Inputs!B7*100)) -> -0.051032761 | K20: =(((Inputs!B6+Inputs!B14+(Inputs!B34*Inputs!B37*(1-Inputs!B30))-(((Inputs!B16*(1+0.25)*Inputs!B15)*0.8*Inputs!B26*Inputs!B28+(Inputs!B16*(1+0.25)*Inputs!B15)*0.8*Inputs!B27*Inputs!B29)*(1-Inputs!B30)))/((Inputs!B7+((Inputs!B16*(1+0.25)*Inputs!B15)*(1-0.8)/Inputs!B8))*100))-(Inputs!B6/(Inputs!B7*100)))/(Inputs!B6/(Inputs!B7*100)) -> -0.054344146 | L20: =(((Inputs!B6+Inputs!B14+(Inputs!B34*Inputs!B37*(1-Inputs!B30))-(((Inputs!B16*(1+0.25)*Inputs!B15)*0.9*Inputs!B26*Inputs!B28+(Inputs!B16*(1+0.25)*Inputs!B15)*0.9*Inputs!B27*Inputs!B29)*(1-Inputs!B30)))/((Inputs!B7+((Inputs!B16*(1+0.25)*Inputs!B15)*(1-0.9)/Inputs!B8))*100))-(Inputs!B6/(Inputs!B7*100)))/(Inputs!B6/(Inputs!B7*100)) -> -0.057773149 | M20: =(((Inputs!B6+Inputs!B14+(Inputs!B34*Inputs!B37*(1-Inputs!B30))-(((Inputs!B16*(1+0.25)*Inputs!B15)*1*Inputs!B26*Inputs!B28+(Inputs!B16*(1+0.25)*Inputs!B15)*1*Inputs!B27*Inputs!B29)*(1-Inputs!B30)))/((Inputs!B7+((Inputs!B16*(1+0.25)*Inputs!B15)*(1-1)/Inputs!B8))*100))-(Inputs!B6/(Inputs!B7*100)))/(Inputs!B6/(Inputs!B7*100)) -> -0.06132615
B21: 0.3 | C21: =(((Inputs!B6+Inputs!B14+(Inputs!B34*Inputs!B37*(1-Inputs!B30))-(((Inputs!B16*(1+0.3)*Inputs!B15)*0*Inputs!B26*Inputs!B28+(Inputs!B16*(1+0.3)*Inputs!B15)*0*Inputs!B27*Inputs!B29)*(1-Inputs!B30)))/((Inputs!B7+((Inputs!B16*(1+0.3)*Inputs!B15)*(1-0)/Inputs!B8))*100))-(Inputs!B6/(Inputs!B7*100)))/(Inputs!B6/(Inputs!B7*100)) -> -0.036593272 | D21: =(((Inputs!B6+Inputs!B14+(Inputs!B34*Inputs!B37*(1-Inputs!B30))-(((Inputs!B16*(1+0.3)*Inputs!B15)*0.1*Inputs!B26*Inputs!B28+(Inputs!B16*(1+0.3)*Inputs!B15)*0.1*Inputs!B27*Inputs!B29)*(1-Inputs!B30)))/((Inputs!B7+((Inputs!B16*(1+0.3)*Inputs!B15)*(1-0.1)/Inputs!B8))*100))-(Inputs!B6/(Inputs!B7*100)))/(Inputs!B6/(Inputs!B7*100)) -> -0.039412938 | E21: =(((Inputs!B6+Inputs!B14+(Inputs!B34*Inputs!B37*(1-Inputs!B30))-(((Inputs!B16*(1+0.3)*Inputs!B15)*0.2*Inputs!B26*Inputs!B28+(Inputs!B16*(1+0.3)*Inputs!B15)*0.2*Inputs!B27*Inputs!B29)*(1-Inputs!B30)))/((Inputs!B7+((Inputs!B16*(1+0.3)*Inputs!B15)*(1-0.2)/Inputs!B8))*100))-(Inputs!B6/(Inputs!B7*100)))/(Inputs!B6/(Inputs!B7*100)) -> -0.04232478 | F21: =(((Inputs!B6+Inputs!B14+(Inputs!B34*Inputs!B37*(1-Inputs!B30))-(((Inputs!B16*(1+0.3)*Inputs!B15)*0.3*Inputs!B26*Inputs!B28+(Inputs!B16*(1+0.3)*Inputs!B15)*0.3*Inputs!B27*Inputs!B29)*(1-Inputs!B30)))/((Inputs!B7+((Inputs!B16*(1+0.3)*Inputs!B15)*(1-0.3)/Inputs!B8))*100))-(Inputs!B6/(Inputs!B7*100)))/(Inputs!B6/(Inputs!B7*100)) -> -0.045333393 | G21: =(((Inputs!B6+Inputs!B14+(Inputs!B34*Inputs!B37*(1-Inputs!B30))-(((Inputs!B16*(1+0.3)*Inputs!B15)*0.4*Inputs!B26*Inputs!B28+(Inputs!B16*(1+0.3)*Inputs!B15)*0.4*Inputs!B27*Inputs!B29)*(1-Inputs!B30)))/((Inputs!B7+((Inputs!B16*(1+0.3)*Inputs!B15)*(1-0.4)/Inputs!B8))*100))-(Inputs!B6/(Inputs!B7*100)))/(Inputs!B6/(Inputs!B7*100)) -> -0.048443682 | H21: =(((Inputs!B6+Inputs!B14+(Inputs!B34*Inputs!B37*(1-Inputs!B30))-(((Inputs!B16*(1+0.3)*Inputs!B15)*0.5*Inputs!B26*Inputs!B28+(Inputs!B16*(1+0.3)*Inputs!B15)*0.5*Inputs!B27*Inputs!B29)*(1-Inputs!B30)))/((Inputs!B7+((Inputs!B16*(1+0.3)*Inputs!B15)*(1-0.5)/Inputs!B8))*100))-(Inputs!B6/(Inputs!B7*100)))/(Inputs!B6/(Inputs!B7*100)) -> -0.05166089 | I21: =(((Inputs!B6+Inputs!B14+(Inputs!B34*Inputs!B37*(1-Inputs!B30))-(((Inputs!B16*(1+0.3)*Inputs!B15)*0.6*Inputs!B26*Inputs!B28+(Inputs!B16*(1+0.3)*Inputs!B15)*0.6*Inputs!B27*Inputs!B29)*(1-Inputs!B30)))/((Inputs!B7+((Inputs!B16*(1+0.3)*Inputs!B15)*(1-0.6)/Inputs!B8))*100))-(Inputs!B6/(Inputs!B7*100)))/(Inputs!B6/(Inputs!B7*100)) -> -0.054990627 | J21: =(((Inputs!B6+Inputs!B14+(Inputs!B34*Inputs!B37*(1-Inputs!B30))-(((Inputs!B16*(1+0.3)*Inputs!B15)*0.7*Inputs!B26*Inputs!B28+(Inputs!B16*(1+0.3)*Inputs!B15)*0.7*Inputs!B27*Inputs!B29)*(1-Inputs!B30)))/((Inputs!B7+((Inputs!B16*(1+0.3)*Inputs!B15)*(1-0.7)/Inputs!B8))*100))-(Inputs!B6/(Inputs!B7*100)))/(Inputs!B6/(Inputs!B7*100)) -> -0.058438902 | K21: =(((Inputs!B6+Inputs!B14+(Inputs!B34*Inputs!B37*(1-Inputs!B30))-(((Inputs!B16*(1+0.3)*Inputs!B15)*0.8*Inputs!B26*Inputs!B28+(Inputs!B16*(1+0.3)*Inputs!B15)*0.8*Inputs!B27*Inputs!B29)*(1-Inputs!B30)))/((Inputs!B7+((Inputs!B16*(1+0.3)*Inputs!B15)*(1-0.8)/Inputs!B8))*100))-(Inputs!B6/(Inputs!B7*100)))/(Inputs!B6/(Inputs!B7*100)) -> -0.062012159 | L21: =(((Inputs!B6+Inputs!B14+(Inputs!B34*Inputs!B37*(1-Inputs!B30))-(((Inputs!B16*(1+0.3)*Inputs!B15)*0.9*Inputs!B26*Inputs!B28+(Inputs!B16*(1+0.3)*Inputs!B15)*0.9*Inputs!B27*Inputs!B29)*(1-Inputs!B30)))/((Inputs!B7+((Inputs!B16*(1+0.3)*Inputs!B15)*(1-0.9)/Inputs!B8))*100))-(Inputs!B6/(Inputs!B7*100)))/(Inputs!B6/(Inputs!B7*100)) -> -0.065717318 | M21: =(((Inputs!B6+Inputs!B14+(Inputs!B34*Inputs!B37*(1-Inputs!B30))-(((Inputs!B16*(1+0.3)*Inputs!B15)*1*Inputs!B26*Inputs!B28+(Inputs!B16*(1+0.3)*Inputs!B15)*1*Inputs!B27*Inputs!B29)*(1-Inputs!B30)))/((Inputs!B7+((Inputs!B16*(1+0.3)*Inputs!B15)*(1-1)/Inputs!B8))*100))-(Inputs!B6/(Inputs!B7*100)))/(Inputs!B6/(Inputs!B7*100)) -> -0.069561822
B22: 0.35 | C22: =(((Inputs!B6+Inputs!B14+(Inputs!B34*Inputs!B37*(1-Inputs!B30))-(((Inputs!B16*(1+0.35)*Inputs!B15)*0*Inputs!B26*Inputs!B28+(Inputs!B16*(1+0.35)*Inputs!B15)*0*Inputs!B27*Inputs!B29)*(1-Inputs!B30)))/((Inputs!B7+((Inputs!B16*(1+0.35)*Inputs!B15)*(1-0)/Inputs!B8))*100))-(Inputs!B6/(Inputs!B7*100)))/(Inputs!B6/(Inputs!B7*100)) -> -0.042422614 | D22: =(((Inputs!B6+Inputs!B14+(Inputs!B34*Inputs!B37*(1-Inputs!B30))-(((Inputs!B16*(1+0.35)*Inputs!B15)*0.1*Inputs!B26*Inputs!B28+(Inputs!B16*(1+0.35)*Inputs!B15)*0.1*Inputs!B27*Inputs!B29)*(1-Inputs!B30)))/((Inputs!B7+((Inputs!B16*(1+0.35)*Inputs!B15)*(1-0.1)/Inputs!B8))*100))-(Inputs!B6/(Inputs!B7*100)))/(Inputs!B6/(Inputs!B7*100)) -> -0.045431334 | E22: =(((Inputs!B6+Inputs!B14+(Inputs!B34*Inputs!B37*(1-Inputs!B30))-(((Inputs!B16*(1+0.35)*Inputs!B15)*0.2*Inputs!B26*Inputs!B28+(Inputs!B16*(1+0.35)*Inputs!B15)*0.2*Inputs!B27*Inputs!B29)*(1-Inputs!B30)))/((Inputs!B7+((Inputs!B16*(1+0.35)*Inputs!B15)*(1-0.2)/Inputs!B8))*100))-(Inputs!B6/(Inputs!B7*100)))/(Inputs!B6/(Inputs!B7*100)) -> -0.048541683 | F22: =(((Inputs!B6+Inputs!B14+(Inputs!B34*Inputs!B37*(1-Inputs!B30))-(((Inputs!B16*(1+0.35)*Inputs!B15)*0.3*Inputs!B26*Inputs!B28+(Inputs!B16*(1+0.35)*Inputs!B15)*0.3*Inputs!B27*Inputs!B29)*(1-Inputs!B30)))/((Inputs!B7+((Inputs!B16*(1+0.35)*Inputs!B15)*(1-0.3)/Inputs!B8))*100))-(Inputs!B6/(Inputs!B7*100)))/(Inputs!B6/(Inputs!B7*100)) -> -0.051758896 | G22: =(((Inputs!B6+Inputs!B14+(Inputs!B34*Inputs!B37*(1-Inputs!B30))-(((Inputs!B16*(1+0.35)*Inputs!B15)*0.4*Inputs!B26*Inputs!B28+(Inputs!B16*(1+0.35)*Inputs!B15)*0.4*Inputs!B27*Inputs!B29)*(1-Inputs!B30)))/((Inputs!B7+((Inputs!B16*(1+0.35)*Inputs!B15)*(1-0.4)/Inputs!B8))*100))-(Inputs!B6/(Inputs!B7*100)))/(Inputs!B6/(Inputs!B7*100)) -> -0.055088579 | H22: =(((Inputs!B6+Inputs!B14+(Inputs!B34*Inputs!B37*(1-Inputs!B30))-(((Inputs!B16*(1+0.35)*Inputs!B15)*0.5*Inputs!B26*Inputs!B28+(Inputs!B16*(1+0.35)*Inputs!B15)*0.5*Inputs!B27*Inputs!B29)*(1-Inputs!B30)))/((Inputs!B7+((Inputs!B16*(1+0.35)*Inputs!B15)*(1-0.5)/Inputs!B8))*100))-(Inputs!B6/(Inputs!B7*100)))/(Inputs!B6/(Inputs!B7*100)) -> -0.058536734 | I22: =(((Inputs!B6+Inputs!B14+(Inputs!B34*Inputs!B37*(1-Inputs!B30))-(((Inputs!B16*(1+0.35)*Inputs!B15)*0.6*Inputs!B26*Inputs!B28+(Inputs!B16*(1+0.35)*Inputs!B15)*0.6*Inputs!B27*Inputs!B29)*(1-Inputs!B30)))/((Inputs!B7+((Inputs!B16*(1+0.35)*Inputs!B15)*(1-0.6)/Inputs!B8))*100))-(Inputs!B6/(Inputs!B7*100)))/(Inputs!B6/(Inputs!B7*100)) -> -0.062109798 | J22: =(((Inputs!B6+Inputs!B14+(Inputs!B34*Inputs!B37*(1-Inputs!B30))-(((Inputs!B16*(1+0.35)*Inputs!B15)*0.7*Inputs!B26*Inputs!B28+(Inputs!B16*(1+0.35)*Inputs!B15)*0.7*Inputs!B27*Inputs!B29)*(1-Inputs!B30)))/((Inputs!B7+((Inputs!B16*(1+0.35)*Inputs!B15)*(1-0.7)/Inputs!B8))*100))-(Inputs!B6/(Inputs!B7*100)))/(Inputs!B6/(Inputs!B7*100)) -> -0.065814683 | K22: =(((Inputs!B6+Inputs!B14+(Inputs!B34*Inputs!B37*(1-Inputs!B30))-(((Inputs!B16*(1+0.35)*Inputs!B15)*0.8*Inputs!B26*Inputs!B28+(Inputs!B16*(1+0.35)*Inputs!B15)*0.8*Inputs!B27*Inputs!B29)*(1-Inputs!B30)))/((Inputs!B7+((Inputs!B16*(1+0.35)*Inputs!B15)*(1-0.8)/Inputs!B8))*100))-(Inputs!B6/(Inputs!B7*100)))/(Inputs!B6/(Inputs!B7*100)) -> -0.069658822 | L22: =(((Inputs!B6+Inputs!B14+(Inputs!B34*Inputs!B37*(1-Inputs!B30))-(((Inputs!B16*(1+0.35)*Inputs!B15)*0.9*Inputs!B26*Inputs!B28+(Inputs!B16*(1+0.35)*Inputs!B15)*0.9*Inputs!B27*Inputs!B29)*(1-Inputs!B30)))/((Inputs!B7+((Inputs!B16*(1+0.35)*Inputs!B15)*(1-0.9)/Inputs!B8))*100))-(Inputs!B6/(Inputs!B7*100)))/(Inputs!B6/(Inputs!B7*100)) -> -0.073650217 | M22: =(((Inputs!B6+Inputs!B14+(Inputs!B34*Inputs!B37*(1-Inputs!B30))-(((Inputs!B16*(1+0.35)*Inputs!B15)*1*Inputs!B26*Inputs!B28+(Inputs!B16*(1+0.35)*Inputs!B15)*1*Inputs!B27*Inputs!B29)*(1-Inputs!B30)))/((Inputs!B7+((Inputs!B16*(1+0.35)*Inputs!B15)*(1-1)/Inputs!B8))*100))-(Inputs!B6/(Inputs!B7*100)))/(Inputs!B6/(Inputs!B7*100)) -> -0.077797493
B23: 0.4 | C23: =(((Inputs!B6+Inputs!B14+(Inputs!B34*Inputs!B37*(1-Inputs!B30))-(((Inputs!B16*(1+0.4)*Inputs!B15)*0*Inputs!B26*Inputs!B28+(Inputs!B16*(1+0.4)*Inputs!B15)*0*Inputs!B27*Inputs!B29)*(1-Inputs!B30)))/((Inputs!B7+((Inputs!B16*(1+0.4)*Inputs!B15)*(1-0)/Inputs!B8))*100))-(Inputs!B6/(Inputs!B7*100)))/(Inputs!B6/(Inputs!B7*100)) -> -0.048181836 | D23: =(((Inputs!B6+Inputs!B14+(Inputs!B34*Inputs!B37*(1-Inputs!B30))-(((Inputs!B16*(1+0.4)*Inputs!B15)*0.1*Inputs!B26*Inputs!B28+(Inputs!B16*(1+0.4)*Inputs!B15)*0.1*Inputs!B27*Inputs!B29)*(1-Inputs!B30)))/((Inputs!B7+((Inputs!B16*(1+0.4)*Inputs!B15)*(1-0.1)/Inputs!B8))*100))-(Inputs!B6/(Inputs!B7*100)))/(Inputs!B6/(Inputs!B7*100)) -> -0.05138346 | E23: =(((Inputs!B6+Inputs!B14+(Inputs!B34*Inputs!B37*(1-Inputs!B30))-(((Inputs!B16*(1+0.4)*Inputs!B15)*0.2*Inputs!B26*Inputs!B28+(Inputs!B16*(1+0.4)*Inputs!B15)*0.2*Inputs!B27*Inputs!B29)*(1-Inputs!B30)))/((Inputs!B7+((Inputs!B16*(1+0.4)*Inputs!B15)*(1-0.2)/Inputs!B8))*100))-(Inputs!B6/(Inputs!B7*100)))/(Inputs!B6/(Inputs!B7*100)) -> -0.054696675 | F23: =(((Inputs!B6+Inputs!B14+(Inputs!B34*Inputs!B37*(1-Inputs!B30))-(((Inputs!B16*(1+0.4)*Inputs!B15)*0.3*Inputs!B26*Inputs!B28+(Inputs!B16*(1+0.4)*Inputs!B15)*0.3*Inputs!B27*Inputs!B29)*(1-Inputs!B30)))/((Inputs!B7+((Inputs!B16*(1+0.4)*Inputs!B15)*(1-0.3)/Inputs!B8))*100))-(Inputs!B6/(Inputs!B7*100)))/(Inputs!B6/(Inputs!B7*100)) -> -0.058127417 | G23: =(((Inputs!B6+Inputs!B14+(Inputs!B34*Inputs!B37*(1-Inputs!B30))-(((Inputs!B16*(1+0.4)*Inputs!B15)*0.4*Inputs!B26*Inputs!B28+(Inputs!B16*(1+0.4)*Inputs!B15)*0.4*Inputs!B27*Inputs!B29)*(1-Inputs!B30)))/((Inputs!B7+((Inputs!B16*(1+0.4)*Inputs!B15)*(1-0.4)/Inputs!B8))*100))-(Inputs!B6/(Inputs!B7*100)))/(Inputs!B6/(Inputs!B7*100)) -> -0.061682055 | H23: =(((Inputs!B6+Inputs!B14+(Inputs!B34*Inputs!B37*(1-Inputs!B30))-(((Inputs!B16*(1+0.4)*Inputs!B15)*0.5*Inputs!B26*Inputs!B28+(Inputs!B16*(1+0.4)*Inputs!B15)*0.5*Inputs!B27*Inputs!B29)*(1-Inputs!B30)))/((Inputs!B7+((Inputs!B16*(1+0.4)*Inputs!B15)*(1-0.5)/Inputs!B8))*100))-(Inputs!B6/(Inputs!B7*100)))/(Inputs!B6/(Inputs!B7*100)) -> -0.065367421 | I23: =(((Inputs!B6+Inputs!B14+(Inputs!B34*Inputs!B37*(1-Inputs!B30))-(((Inputs!B16*(1+0.4)*Inputs!B15)*0.6*Inputs!B26*Inputs!B28+(Inputs!B16*(1+0.4)*Inputs!B15)*0.6*Inputs!B27*Inputs!B29)*(1-Inputs!B30)))/((Inputs!B7+((Inputs!B16*(1+0.4)*Inputs!B15)*(1-0.6)/Inputs!B8))*100))-(Inputs!B6/(Inputs!B7*100)))/(Inputs!B6/(Inputs!B7*100)) -> -0.069190864 | J23: =(((Inputs!B6+Inputs!B14+(Inputs!B34*Inputs!B37*(1-Inputs!B30))-(((Inputs!B16*(1+0.4)*Inputs!B15)*0.7*Inputs!B26*Inputs!B28+(Inputs!B16*(1+0.4)*Inputs!B15)*0.7*Inputs!B27*Inputs!B29)*(1-Inputs!B30)))/((Inputs!B7+((Inputs!B16*(1+0.4)*Inputs!B15)*(1-0.7)/Inputs!B8))*100))-(Inputs!B6/(Inputs!B7*100)))/(Inputs!B6/(Inputs!B7*100)) -> -0.073160291 | K23: =(((Inputs!B6+Inputs!B14+(Inputs!B34*Inputs!B37*(1-Inputs!B30))-(((Inputs!B16*(1+0.4)*Inputs!B15)*0.8*Inputs!B26*Inputs!B28+(Inputs!B16*(1+0.4)*Inputs!B15)*0.8*Inputs!B27*Inputs!B29)*(1-Inputs!B30)))/((Inputs!B7+((Inputs!B16*(1+0.4)*Inputs!B15)*(1-0.8)/Inputs!B8))*100))-(Inputs!B6/(Inputs!B7*100)))/(Inputs!B6/(Inputs!B7*100)) -> -0.077284226 | L23: =(((Inputs!B6+Inputs!B14+(Inputs!B34*Inputs!B37*(1-Inputs!B30))-(((Inputs!B16*(1+0.4)*Inputs!B15)*0.9*Inputs!B26*Inputs!B28+(Inputs!B16*(1+0.4)*Inputs!B15)*0.9*Inputs!B27*Inputs!B29)*(1-Inputs!B30)))/((Inputs!B7+((Inputs!B16*(1+0.4)*Inputs!B15)*(1-0.9)/Inputs!B8))*100))-(Inputs!B6/(Inputs!B7*100)))/(Inputs!B6/(Inputs!B7*100)) -> -0.081571869 | M23: =(((Inputs!B6+Inputs!B14+(Inputs!B34*Inputs!B37*(1-Inputs!B30))-(((Inputs!B16*(1+0.4)*Inputs!B15)*1*Inputs!B26*Inputs!B28+(Inputs!B16*(1+0.4)*Inputs!B15)*1*Inputs!B27*Inputs!B29)*(1-Inputs!B30)))/((Inputs!B7+((Inputs!B16*(1+0.4)*Inputs!B15)*(1-1)/Inputs!B8))*100))-(Inputs!B6/(Inputs!B7*100)))/(Inputs!B6/(Inputs!B7*100)) -> -0.086033165
B24: 0.45 | C24: =(((Inputs!B6+Inputs!B14+(Inputs!B34*Inputs!B37*(1-Inputs!B30))-(((Inputs!B16*(1+0.45)*Inputs!B15)*0*Inputs!B26*Inputs!B28+(Inputs!B16*(1+0.45)*Inputs!B15)*0*Inputs!B27*Inputs!B29)*(1-Inputs!B30)))/((Inputs!B7+((Inputs!B16*(1+0.45)*Inputs!B15)*(1-0)/Inputs!B8))*100))-(Inputs!B6/(Inputs!B7*100)))/(Inputs!B6/(Inputs!B7*100)) -> -0.053872197 | D24: =(((Inputs!B6+Inputs!B14+(Inputs!B34*Inputs!B37*(1-Inputs!B30))-(((Inputs!B16*(1+0.45)*Inputs!B15)*0.1*Inputs!B26*Inputs!B28+(Inputs!B16*(1+0.45)*Inputs!B15)*0.1*Inputs!B27*Inputs!B29)*(1-Inputs!B30)))/((Inputs!B7+((Inputs!B16*(1+0.45)*Inputs!B15)*(1-0.1)/Inputs!B8))*100))-(Inputs!B6/(Inputs!B7*100)))/(Inputs!B6/(Inputs!B7*100)) -> -0.057270404 | E24: =(((Inputs!B6+Inputs!B14+(Inputs!B34*Inputs!B37*(1-Inputs!B30))-(((Inputs!B16*(1+0.45)*Inputs!B15)*0.2*Inputs!B26*Inputs!B28+(Inputs!B16*(1+0.45)*Inputs!B15)*0.2*Inputs!B27*Inputs!B29)*(1-Inputs!B30)))/((Inputs!B7+((Inputs!B16*(1+0.45)*Inputs!B15)*(1-0.2)/Inputs!B8))*100))-(Inputs!B6/(Inputs!B7*100)))/(Inputs!B6/(Inputs!B7*100)) -> -0.060790677 | F24: =(((Inputs!B6+Inputs!B14+(Inputs!B34*Inputs!B37*(1-Inputs!B30))-(((Inputs!B16*(1+0.45)*Inputs!B15)*0.3*Inputs!B26*Inputs!B28+(Inputs!B16*(1+0.45)*Inputs!B15)*0.3*Inputs!B27*Inputs!B29)*(1-Inputs!B30)))/((Inputs!B7+((Inputs!B16*(1+0.45)*Inputs!B15)*(1-0.3)/Inputs!B8))*100))-(Inputs!B6/(Inputs!B7*100)))/(Inputs!B6/(Inputs!B7*100)) -> -0.064439711 | G24: =(((Inputs!B6+Inputs!B14+(Inputs!B34*Inputs!B37*(1-Inputs!B30))-(((Inputs!B16*(1+0.45)*Inputs!B15)*0.4*Inputs!B26*Inputs!B28+(Inputs!B16*(1+0.45)*Inputs!B15)*0.4*Inputs!B27*Inputs!B29)*(1-Inputs!B30)))/((Inputs!B7+((Inputs!B16*(1+0.45)*Inputs!B15)*(1-0.4)/Inputs!B8))*100))-(Inputs!B6/(Inputs!B7*100)))/(Inputs!B6/(Inputs!B7*100)) -> -0.068224703 | H24: =(((Inputs!B6+Inputs!B14+(Inputs!B34*Inputs!B37*(1-Inputs!B30))-(((Inputs!B16*(1+0.45)*Inputs!B15)*0.5*Inputs!B26*Inputs!B28+(Inputs!B16*(1+0.45)*Inputs!B15)*0.5*Inputs!B27*Inputs!B29)*(1-Inputs!B30)))/((Inputs!B7+((Inputs!B16*(1+0.45)*Inputs!B15)*(1-0.5)/Inputs!B8))*100))-(Inputs!B6/(Inputs!B7*100)))/(Inputs!B6/(Inputs!B7*100)) -> -0.072153396 | I24: =(((Inputs!B6+Inputs!B14+(Inputs!B34*Inputs!B37*(1-Inputs!B30))-(((Inputs!B16*(1+0.45)*Inputs!B15)*0.6*Inputs!B26*Inputs!B28+(Inputs!B16*(1+0.45)*Inputs!B15)*0.6*Inputs!B27*Inputs!B29)*(1-Inputs!B30)))/((Inputs!B7+((Inputs!B16*(1+0.45)*Inputs!B15)*(1-0.6)/Inputs!B8))*100))-(Inputs!B6/(Inputs!B7*100)))/(Inputs!B6/(Inputs!B7*100)) -> -0.076234132 | J24: =(((Inputs!B6+Inputs!B14+(Inputs!B34*Inputs!B37*(1-Inputs!B30))-(((Inputs!B16*(1+0.45)*Inputs!B15)*0.7*Inputs!B26*Inputs!B28+(Inputs!B16*(1+0.45)*Inputs!B15)*0.7*Inputs!B27*Inputs!B29)*(1-Inputs!B30)))/((Inputs!B7+((Inputs!B16*(1+0.45)*Inputs!B15)*(1-0.7)/Inputs!B8))*100))-(Inputs!B6/(Inputs!B7*100)))/(Inputs!B6/(Inputs!B7*100)) -> -0.080475911 | K24: =(((Inputs!B6+Inputs!B14+(Inputs!B34*Inputs!B37*(1-Inputs!B30))-(((Inputs!B16*(1+0.45)*Inputs!B15)*0.8*Inputs!B26*Inputs!B28+(Inputs!B16*(1+0.45)*Inputs!B15)*0.8*Inputs!B27*Inputs!B29)*(1-Inputs!B30)))/((Inputs!B7+((Inputs!B16*(1+0.45)*Inputs!B15)*(1-0.8)/Inputs!B8))*100))-(Inputs!B6/(Inputs!B7*100)))/(Inputs!B6/(Inputs!B7*100)) -> -0.084888458 | L24: =(((Inputs!B6+Inputs!B14+(Inputs!B34*Inputs!B37*(1-Inputs!B30))-(((Inputs!B16*(1+0.45)*Inputs!B15)*0.9*Inputs!B26*Inputs!B28+(Inputs!B16*(1+0.45)*Inputs!B15)*0.9*Inputs!B27*Inputs!B29)*(1-Inputs!B30)))/((Inputs!B7+((Inputs!B16*(1+0.45)*Inputs!B15)*(1-0.9)/Inputs!B8))*100))-(Inputs!B6/(Inputs!B7*100)))/(Inputs!B6/(Inputs!B7*100)) -> -0.089482297 | M24: =(((Inputs!B6+Inputs!B14+(Inputs!B34*Inputs!B37*(1-Inputs!B30))-(((Inputs!B16*(1+0.45)*Inputs!B15)*1*Inputs!B26*Inputs!B28+(Inputs!B16*(1+0.45)*Inputs!B15)*1*Inputs!B27*Inputs!B29)*(1-Inputs!B30)))/((Inputs!B7+((Inputs!B16*(1+0.45)*Inputs!B15)*(1-1)/Inputs!B8))*100))-(Inputs!B6/(Inputs!B7*100)))/(Inputs!B6/(Inputs!B7*100)) -> -0.094268836
B26: 📌 HOW TO READ: Each cell = (Pro Forma EPS − Standalone EPS) ÷ Standalone EPS | 🟡 Yellow = current deal (30% premium, 60% cash) | Change any Inputs tab value → both tables update instantly
B27: 💡 KEY INSIGHT: Higher cash % = larger financing drag = more dilutive. Higher premium = bigger deal = more dilutive. Table 2 vs Table 1 shows synergy ramp narrowing the dilution gap by Year 3.

Sheet Leverage
B1: LEVERAGE & COVENANT ANALYSIS — PRO FORMA COMBINED ENTITY
B2: Kotak Mahindra Bank (Acquirer) × IDFC First Bank (Target) | All values ₹ Crore | Formulas reference Inputs & Calculations tabs
B4: A · PRO FORMA LEVERAGE BUILD (₹ Crore)
B5: Acquirer Existing Net Borrowings (₹ Cr) | C5: =Inputs!B11 -> 185000
B6: (+) New Debt Raised for Acquisition (₹ Cr) | C6: =Calculations!B8 -> 32195.903
B7: (+) Target Existing Net Borrowings Assumed (₹ Cr) | C7: =Inputs!B18 -> 48354
B8: Pro Forma Combined Net Borrowings (₹ Cr) | C8: =Inputs!B11+Calculations!B8+Inputs!B18 -> 265549.9
B10: Acquirer PPOP (₹ Cr) | C10: =Inputs!B10 -> 24800
B11: (+) Target PPOP (₹ Cr) | C11: =Inputs!B17 -> 4800
B12: Pro Forma Combined PPOP (₹ Cr) | C12: =Inputs!B10+Inputs!B17 -> 29600
B14: Pro Forma Net Borrowings / PPOP (x) | C14: =Leverage!C8/Leverage!C12 -> 8.9712805
B16: B · COVENANT HEADROOM (Net Borrowings / PPOP vs Threshold)
B17: Covenant Threshold (Net Borrowings / PPOP ≤ x) | C17: =Inputs!B42 -> 8
B18: Pro Forma Leverage Ratio (x) | C18: =Leverage!C14 -> 8.9712805
B19: Headroom (Threshold − Actual) (x) | C19: =Inputs!B42-Leverage!C18 -> -0.9712805
B20: Max Additional Debt Before Covenant Breach (₹ Cr) | C20: =(Inputs!B42-Leverage!C18)*Leverage!C12 -> -28749.903
B21: Covenant Status | C21: =IF(C19>1,"✔ SAFE (headroom > 1.0x)",IF(C19>0.5,"⚠ WATCH (headroom 0.5–1.0x)",IF(C19>0,"✘ TIGHT (headroom < 0.5x)","✘ BREACH (ratio exceeds threshold)"))) -> ✘ BREACH (ratio exceeds threshold)
B23: C · RBI REGULATORY CONTEXT — CAPITAL ADEQUACY (CRAR) [Reference Only]
B24: Note: For banks, RBI monitors leverage primarily via CRAR (Capital Adequacy Ratio) under Basel III. The Net Borrowings/PPOP ratio above is an internal management metric. CRAR figures below are actuals from FY2026 filings — for reference only.
B25: Entity | C25: CRAR (Basel III) | D25: Tier 1 Ratio | E25: RBI Minimum CRAR | F25: Headroom vs Min | G25: Status
B26: Kotak Mahindra Bank | C26: 21.96% | D26: 21.28% | E26: 11.5% | F26: 10.46% | G26: ✔ Well Capitalised
B27: IDFC First Bank | C27: 15.60% | D27: 13.92% | E27: 11.5% | F27: 4.10% | G27: ✔ Well Capitalised
B28: Pro Forma (illustrative) | C28: TBD post-merger | D28: TBD post-merger | E28: 11.5% | F28: Pending integration | G28: Subject to RBI approval
B30: D · 5-YEAR DELEVERAGING SCHEDULE (Pro Forma Leverage Ratio by Year)
B31: Assumed Annual PPOP Growth Rate (%) — type to change | C31: 0.12
B32: Assumed Annual Debt Amortisation Rate (%) — type to change | C32: 0.05
B34: Metric | E34: Year 0 (Close) | F34: Year 1 | G34: Year 2 | H34: Year 3 | I34: Year 4 | J34: Year 5
B35: Combined PPOP (₹ Cr) | E35: =Leverage!C12 -> 29600 | F35: =Leverage!E35*(1+Leverage!C31)^1 -> 33152 | G35: =Leverage!E35*(1+Leverage!C31)^2 -> 37130.24 | H35: =Leverage!E35*(1+Leverage!C31)^3 -> 41585.869 | I35: =Leverage!E35*(1+Leverage!C31)^4 -> 46576.173 | J35: =Leverage!E35*(1+Leverage!C31)^5 -> 52165.314
B36: Net Borrowings (₹ Cr) | E36: =Leverage!C8 -> 265549.9 | F36: =Leverage!E36*(1-Leverage!C32)^1 -> 252272.41 | G36: =Leverage!E36*(1-Leverage!C32)^2 -> 239658.79 | H36: =Leverage!E36*(1-Leverage!C32)^3 -> 227675.85 | I36: =Leverage!E36*(1-Leverage!C32)^4 -> 216292.06 | J36: =Leverage!E36*(1-Leverage!C32)^5 -> 205477.45
B37: Net Borrowings / PPOP (x) | E37: =Leverage!E36/Leverage!E35 -> 8.9712805 | F37: =Leverage!F36/Leverage!F35 -> 7.6095683 | G37: =Leverage!G36/Leverage!G35 -> 6.4545445 | H37: =Leverage!H36/Leverage!H35 -> 5.4748369 | I37: =Leverage!I36/Leverage!I35 -> 4.6438348 | J37: =Leverage!J36/Leverage!J35 -> 3.9389671
B38: Covenant Threshold (x) [reference] | E38: =Inputs!B42 -> 8 | F38: =Inputs!B42 -> 8 | G38: =Inputs!B42 -> 8 | H38: =Inputs!B42 -> 8 | I38: =Inputs!B42 -> 8 | J38: =Inputs!B42 -> 8
B39: Headroom (Threshold − Leverage) (x) | E39: =Leverage!E38-Leverage!E37 -> -0.9712805 | F39: =Leverage!F38-Leverage!F37 -> 0.39043172 | G39: =Leverage!G38-Leverage!G37 -> 1.5454555 | H39: =Leverage!H38-Leverage!H37 -> 2.5251631 | I39: =Leverage!I38-Leverage!I37 -> 3.3561652 | J39: =Leverage!J38-Leverage!J37 -> 4.0610329
B41: 📌 PPOP growth rate and debt amortisation rate (Section D, blue cells) are the only typed inputs on this tab. All other values flow from Inputs and Calculations tabs. Adjust growth/amortisation to model deleveraging scenarios. | RBI CRAR figures (Section C) are FY2026 actuals — hardcoded for reference.

Sheet ⚙ PQ_Setup
A1: ⚙ POWER QUERY SETUP GUIDE — Live Share Prices (KOTAKBANK & IDFCFIRSTB)
A2: Follow these steps ONCE to connect live NSE share prices. Takes < 2 minutes.
A4: STEP 1 — Open Power Query Editor
A5: In Excel: Data tab → Get Data → Launch Power Query Editor
A7: STEP 2 — Create Query: AcquirerLivePrice (Kotak Mahindra Bank)
A8: Home → New Source → Other Sources → Blank Query
A9: In the formula bar (or Advanced Editor), paste the M code below:
A11: let
A12: Source = Json.Document(Web.Contents("https://query1.finance.yahoo.com/v8/finance/chart/KOTAKBANK.NS?interval=1d&range=1d")),
A13: chart = Source[chart],
A14: result = chart[result]{0},
A15: meta = result[meta],
... A49: in the purple cells will keep the model live even if the API is unreachable.
